Workbook

Sheet TASK note
A6: Task
A8: 1 | B8: In the services table find people who we can count as ‘new’ by identifying those who commenced long term support as their first service during the year 2023-24
A10: 2 | B10: How many new starts were there per month, by type?
A12: 3 | B12: How many have autism?
A14: 4 | B14: By reference to the assessments completed table, calculate the median calendar days from assessment to long term support for new people
A16: 5 | B16: Present your results in a useful visual or visuals
A18: 6 | B18: What are the limitations of these data and what other areas would you consider useful to follow up?
A21: Notes
A22: The reporting year runs from 1st April to 31st March
A23: All data are fictional
G29: .

Sheet Raw Data 1
A1: Service ID | B1: Person ID | C1: Service Description | D1: Service Class | E1: Start Date | F1: End Date | G1: Service Provider
A2: 1 | B2: 1971 | C2: Personal Budget | D2: Long Term | E2: 44840 | F2: 44916 | G2: Green Ltd
A3: 2 | B3: 3823 | C3: Personal Budget | D3: Long Term | E3: 44832 | F3: 45114 | G3: Wells, Levy and Martin
A4: 3 | B4: 2820 | C4: Personal Budget | D4: Long Term | E4: 45057 | G4: Wood Group
A5: 4 | B5: 903 | C5: Equipment | D5: Low level | E5: 44765 | F5: 44953 | G5: Flores-Jones
A6: 5 | B6: 365 | C6: Personal Budget | D6: Long Term | E6: 43959 | F6: 44805 | G6: Byrd, Bradford and Jacobs
A7: 6 | B7: 4259 | C7: Nursing Home | D7: Long Term | E7: 44693 | F7: 45440 | G7: Sanders-Moore
A8: 7 | B8: 3120 | C8: Nursing Home | D8: Long Term | E8: 44739 | G8: Montgomery, Lee and Anderson
A9: 8 | B9: 2559 | C9: Residential Home | D9: Long Term | E9: 44731 | F9: 45208 | G9: Wilson, Hernandez and Allen
A10: 9 | B10: 1864 | C10: Direct Payment | D10: Long Term | E10: 44941 | F10: 44969 | G10: Jones, Phillips and Singleton
A11: 10 | B11: 116 | C11: Personal Budget | D11: Long Term | E11: 44898 | G11: Mcguire and Sons
A12: 11 | B12: 2385 | C12: Personal Budget | D12: Long Term | E12: 44467 | F12: 44785 | G12: Parsons-Sexton
A13: 12 | B13: 4977 | C13: Homecare | D13: Long Term | E13: 44891 | F13: 45034 | G13: Martinez Ltd
A14: 13 | B14: 3936 | C14: Equipment | D14: Low level | E14: 45077 | F14: 45307 | G14: Brock LLC
A15: 14 | B15: 4936 | C15: Direct Payment | D15: Long Term | E15: 45096 | F15: 45271 | G15: Cox LLC
A16: 15 | B16: 2491 | C16: Residential Home | D16: Long Term | E16: 45211 | F16: 45362 | G16: White-Murphy
A17: 16 | B17: 943 | C17: Direct Payment | D17: Long Term | E17: 44878 | G17: York, Williams and Young
A18: 17 | B18: 1725 | C18: Personal Budget | D18: Long Term | E18: 45016 | F18: 45325 | G18: Rowe-Price
A19: 18 | B19: 2335 | C19: Homecare | D19: Long Term | E19: 44986 | G19: Dodson PLC
A20: 19 | B20: 2768 | C20: Equipment | D20: Low level | E20: 44629 | F20: 45342 | G20: Carey Ltd
A21: 20 | B21: 1138 | C21: Residential Home | D21: Long Term | E21: 45143 | G21: Lamb and Sons
A22: 21 | B22: 2528 | C22: Direct Payment | D22: Long Term | E22: 45308 | F22: 45365 | G22: Kramer, Byrd and Walker
A23: 22 | B23: 4118 | C23: Residential Home | D23: Long Term | E23: 43899 | F23: 44515 | G23: Holloway-Orr
A24: 23 | B24: 3421 | C24: Personal Budget | D24: Long Term | E24: 44530 | F24: 45404 | G24: Mcknight Inc
A25: 24 | B25: 4779 | C25: Residential Home | D25: Long Term | E25: 44187 | F25: 45254 | G25: Rogers, Nichols and Huerta
A26: 25 | B26: 3907 | C26: Homecare | D26: Long Term | E26: 45367 | F26: 45528 | G26: Thornton-Martin
A27: 26 | B27: 3638 | C27: Residential Home | D27: Long Term | E27: 44325 | G27: Vasquez-Thompson
A28: 27 | B28: 2954 | C28: Nursing Home | D28: Long Term | E28: 44221 | G28: Sims-Cohen
A29: 28 | B29: 2368 | C29: Homecare | D29: Long Term | E29: 45289 | F29: 45384 | G29: Williams, Abbott and Goodwin
A30: 29 | B30: 4222 | C30: Direct Payment | D30: Short Term | E30: 45529 | F30: 45532 | G30: Mercado LLC
A31: 30 | B31: 277 | C31: Equipment | D31: Low level | E31: 44200 | F31: 44389 | G31: Smith-Guerrero
A32: 31 | B32: 2000 | C32: Equipment | D32: Low level | E32: 44085 | F32: 44304 | G32: Moore-Carlson
A33: 32 | B33: 1228 | C33: Personal Budget | D33: Long Term | E33: 45445 | F33: 45513 | G33: Navarro Group
A34: 33 | B34: 3753 | C34: Personal Budget | D34: Long Term | E34: 44365 | F34: 44992 | G34: Williams Group
A35: 34 | B35: 3736 | C35: Nursing Home | D35: Long Term | E35: 44755 | F35: 44997 | G35: Wright-Tucker
A36: 35 | B36: 696 | C36: Direct Payment | D36: Long Term | E36: 44177 | G36: Bautista Ltd
A37: 36 | B37: 1310 | C37: Equipment | D37: Low level | E37: 45112 | F37: 45214 | G37: Harper Group
A38: 37 | B38: 4153 | C38: Equipment | D38: Low level | E38: 44344 | F38: 44625 | G38: Bennett, Campos and Sanchez
A39: 38 | B39: 3235 | C39: Equipment | D39: Low level | E39: 45290 | F39: 45445 | G39: Perez-Cervantes
A40: 39 | B40: 4115 | C40: Equipment | D40: Low level | E40: 44939 | G40: Griffith PLC
A41: 40 | B41: 2312 | C41: Residential Home | D41: Short Term | E41: 44419 | F41: 44453 | G41: Kaufman LLC
A42: 41 | B42: 2842 | C42: Direct Payment | D42: Long Term | E42: 45074 | F42: 45469 | G42: Murray LLC
A43: 42 | B43: 4209 | C43: Homecare | D43: Long Term | E43: 45032 | G43: Daniels, Rodriguez and Oliver
A44: 43 | B44: 3560 | C44: Homecare | D44: Long Term | E44: 44372 | F44: 45216 | G44: Brown-Smith
A45: 44 | B45: 3399 | C45: Nursing Home | D45: Long Term | E45: 44141 | F45: 45150 | G45: Boyer, Barrera and Williams
A46: 45 | B46: 542 | C46: Residential Home | D46: Long Term | E46: 44999 | F46: 45525 | G46: Romero, Duncan and Williams
A47: 46 | B47: 2695 | C47: Equipment | D47: Low level | E47: 45502 | G47: Moran-Davis
A48: 47 | B48: 4675 | C48: Equipment | D48: Low level | E48: 45490 | F48: 45508 | G48: Carter-Dominguez
A49: 48 | B49: 1089 | C49: Personal Budget | D49: Long Term | E49: 44222 | F49: 44849 | G49: Fuller LLC
A50: 49 | B50: 3364 | C50: Personal Budget | D50: Long Term | E50: 44651 | F50: 45255 | G50: Suarez, Miller and Wright
A51: 50 | B51: 25 | C51: Nursing Home | D51: Long Term | E51: 45433 | G51: Morgan-Mckay
A52: 51 | B52: 1573 | C52: Equipment | D52: Low level | E52: 44147 | G52: Pham, Owens and Ferguson
A53: 52 | B53: 2959 | C53: Nursing Home | D53: Long Term | E53: 45249 | F53: 45410 | G53: Booker-Mckinney
A54: 53 | B54: 4237 | C54: Residential Home | D54: Long Term | E54: 45102 | G54: Crane-King
A55: 54 | B55: 1768 | C55: Homecare | D55: Long Term | E55: 44978 | F55: 45253 | G55: Phillips Group
A56: 55 | B56: 4744 | C56: Equipment | D56: Low level | E56: 45088 | F56: 45287 | G56: Baker-Cowan
A57: 56 | B57: 2236 | C57: Direct Payment | D57: Long Term | E57: 45387 | F57: 45465 | G57: Lucas and Sons
A58: 57 | B58: 201 | C58: Residential Home | D58: Long Term | E58: 44576 | F58: 45511 | G58: Brennan, Grant and Williams
A59: 58 | B59: 3199 | C59: Equipment | D59: Low level | E59: 45450 | G59: Branch PLC
A60: 59 | B60: 257 | C60: Direct Payment | D60: Long Term | E60: 44528 | G60: Williams Ltd
A61: 60 | B61: 3748 | C61: Personal Budget | D61: Long Term | E61: 43822 | G61: Kennedy, Reynolds and Sanchez
A62: 61 | B62: 4643 | C62: Nursing Home | D62: Long Term | E62: 44048 | F62: 45347 | G62: Carpenter, Hicks and Estrada
A63: 62 | B63: 2242 | C63: Personal Budget | D63: Long Term | E63: 43753 | F63: 45106 | G63: Carey, Anderson and Fisher
A64: 63 | B64: 3176 | C64: Homecare | D64: Long Term | E64: 43707 | G64: Mccann Inc
A65: 64 | B65: 3607 | C65: Personal Budget | D65: Long Term | E65: 44895 | F65: 45280 | G65: Miller, Page and Lynn
A66: 65 | B66: 3337 | C66: Equipment | D66: Low level | E66: 43827 | F66: 45039 | G66: Clark-Weber
A67: 66 | B67: 4898 | C67: Direct Payment | D67: Long Term | E67: 45197 | F67: 45254 | G67: Oconnor Group
A68: 67 | B68: 414 | C68: Personal Budget | D68: Long Term | E68: 44599 | G68: Acosta, Roberts and Rivera
A69: 68 | B69: 2015 | C69: Equipment | D69: Low level | E69: 44241 | F69: 44273 | G69: Perez, Thomas and Moore
A70: 69 | B70: 1382 | C70: Homecare | D70: Long Term | E70: 45237 | G70: Weaver, Whitehead and Carter
A71: 70 | B71: 1099 | C71: Direct Payment | D71: Long Term | E71: 45464 | F71: 45475 | G71: Floyd, Love and Weber
A72: 71 | B72: 3427 | C72: Personal Budget | D72: Long Term | E72: 44973 | F72: 45149 | G72: Smith LLC
A73: 72 | B73: 3656 | C73: Nursing Home | D73: Long Term | E73: 44206 | F73: 44265 | G73: Kennedy and Sons
A74: 73 | B74: 910 | C74: Nursing Home | D74: Long Term | E74: 45158 | F74: 45354 | G74: Williams-Cooper
A75: 74 | B75: 188 | C75: Direct Payment | D75: Long Term | E75: 45105 | F75: 45280 | G75: Woodward-Huber
A76: 75 | B76: 4045 | C76: Nursing Home | D76: Long Term | E76: 45417 | F76: 45526 | G76: Herrera, Martin and Gibson
A77: 76 | B77: 3757 | C77: Personal Budget | D77: Long Term | E77: 44312 | G77: Nunez Inc
A78: 77 | B78: 2016 | C78: Personal Budget | D78: Long Term | E78: 44694 | F78: 44886 | G78: Marshall Group
A79: 78 | B79: 2093 | C79: Direct Payment | D79: Long Term | E79: 43751 | F79: 45089 | G79: Bryant, Lopez and Thompson
A80: 79 | B80: 3645 | C80: Personal Budget | D80: Long Term | E80: 44067 | F80: 45331 | G80: Martin LLC
A81: 80 | B81: 2131 | C81: Equipment | D81: Low level | E81: 44546 | F81: 45415 | G81: Carlson-Little
A82: 81 | B82: 358 | C82: Homecare | D82: Long Term | E82: 45093 | F82: 45489 | G82: Glass Ltd
A83: 82 | B83: 2423 | C83: Nursing Home | D83: Long Term | E83: 44894 | G83: Compton Ltd
A84: 83 | B84: 4258 | C84: Equipment | D84: Low level | E84: 44672 | F84: 45213 | G84: Smith-Perry
A85: 84 | B85: 4546 | C85: Direct Payment | D85: Long Term | E85: 45120 | G85: Adams, Smith and Coleman
A86: 85 | B86: 1498 | C86: Nursing Home | D86: Long Term | E86: 44470 | F86: 45328 | G86: Jones-Cantu
A87: 86 | B87: 2159 | C87: Equipment | D87: Low level | E87: 45305 | G87: West-Stevens
A88: 87 | B88: 2556 | C88: Personal Budget | D88: Long Term | E88: 43834 | F88: 44248 | G88: Stewart, Johnson and Johnson
A89: 88 | B89: 2343 | C89: Direct Payment | D89: Long Term | E89: 44684 | F89: 44722 | G89: Ross Ltd
A90: 89 | B90: 2952 | C90: Direct Payment | D90: Long Term | E90: 44529 | F90: 44543 | G90: Walker LLC
A91: 90 | B91: 1239 | C91: Nursing Home | D91: Long Term | E91: 44339 | F91: 44631 | G91: Petersen, Moore and Spencer
A92: 91 | B92: 974 | C92: Personal Budget | D92: Short Term | E92: 45113 | F92: 45119 | G92: Williams LLC
A93: 92 | B93: 4728 | C93: Nursing Home | D93: Long Term | E93: 44622 | G93: Smith and Sons
A94: 93 | B94: 3966 | C94: Residential Home | D94: Long Term | E94: 44119 | G94: Miller-Garcia
A95: 94 | B95: 1051 | C95: Equipment | D95: Low level | E95: 43990 | F95: 44589 | G95: Nguyen, Johnson and Ramos
A96: 95 | B96: 3702 | C96: Residential Home | D96: Long Term | E96: 44175 | F96: 44569 | G96: Ferguson Inc
A97: 96 | B97: 2781 | C97: Equipment | D97: Low level | E97: 44865 | F97: 45531 | G97: Blankenship LLC
A98: 97 | B98: 1589 | C98: Homecare | D98: Long Term | E98: 45120 | F98: 45191 | G98: Smith, Perez and Miller
A99: 98 | B99: 3879 | C99: Direct Payment | D99: Long Term | E99: 45367 | F99: 45524 | G99: Hernandez, Perez and Harmon
A100: 99 | B100: 2369 | C100: Nursing Home | D100: Long Term | E100: 45379 | F100: 45445 | G100: Haney PLC
...

Sheet Raw Data 2
A1: Person ID | B1: Event | C1: Assessment start | D1: Assessment end
A2: 1687 | B2: Assessment | C2: 45017 | D2: 45023
A3: 2116 | B3: Assessment | C3: 45017 | D3: 45022
A4: 2820 | B4: Assessment | C4: 45017 | D4: 45022
A5: 3514 | B5: Assessment | C5: 45017 | D5: 45022
A6: 3730 | B6: Assessment | C6: 45017 | D6: 45023
A7: 508 | B7: Assessment | C7: 45018 | D7: 45023
A8: 517 | B8: Assessment | C8: 45018 | D8: 45023
A9: 4209 | B9: Assessment | C9: 45019 | D9: 45025
A10: 2549 | B10: Assessment | C10: 45020 | D10: 45025
A11: 2750 | B11: Assessment | C11: 45020 | D11: 45025
A12: 446 | B12: Assessment | C12: 45021 | D12: 45026
A13: 2557 | B13: Assessment | C13: 45021 | D13: 45026
... A1089: 787 | B1089: Assessment | C1089: 45527 | D1089: 45537

Sheet Raw Data 3
A1: Person ID | B1: Gender | C1: Health condition | D1: Age band | E1: Accommodation status
A2: 1 | B2: Male | D2: 65+ | E2: Tenant: Private landlord
A3: 2 | B3: Female | D3: 18-64 | E3: Tenant: Private landlord
A4: 3 | B4: Female | D4: 18-64 | E4: Unknown
A5: 4 | B5: Male | D5: 18-64 | E5: Tenant: Private landlord
A6: 5 | B6: Male | D6: 18-64 | E6: Registered care home
A7: 6 | B7: Female | D7: 65+ | E7: Tenant: Private landlord
A8: 7 | B8: Male | D8: 18-64 | E8: Tenant: Local authority or other social housing provider
A9: 8 | B9: Female | C9: Dementia | D9: 65+ | E9: Tenant: Private landlord
A10: 9 | B10: Male | D10: 65+ | E10: Tenant: Private landlord
A11: 10 | B11: Male | C11: ASD | D11: 18-64 | E11: Tenant: Private landlord
A12: 11 | B12: Male | D12: 18-64 | E12: Tenant: Private landlord
A13: 12 | B13: Male | D13: 18-64 | E13: Tenant: Private landlord
A14: 13 | B14: Male | C14: Autism | D14: 18-64 | E14: Registered care home
A15: 14 | B15: Male | D15: 65+ | E15: Unknown
A16: 15 | B16: Female | D16: 18-64 | E16: Tenant: Private landlord
A17: 16 | B17: Female | D17: 65+ | E17: Registered care home
A18: 17 | B18: Male | D18: 18-64 | E18: Registered care home
A19: 18 | B19: Male | D19: 18-64 | E19: Tenant: Private landlord
A20: 19 | B20: Female | D20: 65+ | E20: Tenant: Private landlord
A21: 20 | B21: Female | D21: 18-64 | E21: Unknown
A22: 21 | B22: Female | D22: 18-64 | E22: Registered care home
A23: 22 | B23: Male | D23: 18-64 | E23: Tenant: Private landlord
A24: 23 | B24: Male | D24: 18-64 | E24: Tenant: Private landlord
A25: 24 | B25: Female | D25: 18-64 | E25: Tenant: Private landlord
A26: 25 | B26: Male | D26: 65+ | E26: Tenant: Private landlord
... A29: 28 | B29: Female | D29: 65+ | E29: Tenant: Private landlord
A30: 29 | B30: Male | C30: Dementia | D30: 65+ | E30: Unknown
A31: 30 | B31: Female | D31: 18-64 | E31: Tenant: Private landlord
A32: 31 | B32: Female | D32: 18-64 | E32: Tenant: Local authority or other social housing provider
A33: 32 | B33: Male | C33: Autism | D33: 18-64 | E33: Tenant: Private landlord
A34: 33 | B34: Female | C34: Partial sight/sight impaired | D34: 18-64 | E34: Registered care home
A35: 34 | B35: Female | D35: 18-64 | E35: Tenant: Private landlord
A36: 35 | B36: Female | D36: 65+ | E36: Tenant: Private landlord
A37: 36 | B37: Female | D37: 65+ | E37: Tenant: Private landlord
A38: 37 | B38: Male | D38: 65+ | E38: Tenant: Private landlord
A39: 38 | B39: Female | D39: 18-64 | E39: Unknown
A40: 39 | B40: Male | D40: 18-64 | E40: Tenant: Private landlord
A41: 40 | B41: Female | D41: 65+ | E41: Tenant: Private landlord
A42: 41 | B42: Female | D42: 65+ | E42: Unknown
A43: 42 | B43: Male | D43: 65+ | E43: Unknown
A44: 43 | B44: Female | D44: 18-64 | E44: Registered care home
A45: 44 | B45: Male | D45: 18-64 | E45: Registered care home
A46: 45 | B46: Female | D46: 18-64 | E46: Tenant: Private landlord
... A49: 48 | B49: Female | D49: 18-64 | E49: Tenant: Private landlord
A50: 49 | B50: Male | C50: Blind/severely sight impaired | D50: 18-64 | E50: Registered nursing home
A51: 50 | B51: Female | D51: 18-64 | E51: Registered care home
A52: 51 | B52: Female | D52: 18-64 | E52: Tenant: Private landlord
A53: 52 | B53: Female | D53: 18-64 | E53: Tenant: Private landlord
A54: 53 | B54: Female | D54: 18-64 | E54: Unknown
A55: 54 | B55: Male | D55: 18-64 | E55: Tenant: Private landlord
A56: 55 | B56: Female | D56: 65+ | E56: Tenant: Private landlord
A57: 56 | B57: Male | D57: 18-64 | E57: Tenant: Private landlord
A58: 57 | B58: Female | D58: 65+ | E58: Tenant: Private landlord
A59: 58 | B59: Male | D59: 18-64 | E59: Tenant: Local authority or other social housing provider
A60: 59 | B60: Female | D60: 65+ | E60: Tenant: Private landlord
A61: 60 | B61: Male | D61: 18-64 | E61: Tenant: Private landlord
A62: 61 | B62: Female | D62: 18-64 | E62: Tenant: Private landlord
... A85: 84 | B85: Female | D85: 65+ | E85: Registered care home
A86: 85 | B86: Male | C86: Autism | D86: 18-64 | E86: Settled mainstream housing with family or friends
A87: 86 | B87: Female | D87: 18-64 | E87: Tenant: Local authority or other social housing provider
A88: 87 | B88: Male | D88: 65+ | E88: Sheltered housing
A89: 88 | B89: Female | D89: 18-64 | E89: Owner occupier or shared ownership scheme
A90: 89 | B90: Male | D90: 18-64 | E90: Owner occupier or shared ownership scheme
A91: 90 | B91: Female | D91: 65+ | E91: Registered care home
A92: 91 | B92: Female | D92: 18-64 | E92: Registered care home
A93: 92 | B93: Male | D93: 18-64 | E93: Owner occupier or shared ownership scheme
A94: 93 | B94: Male | D94: 65+ | E94: Staying with family or friends as a short term guest
A95: 94 | B95: Female | D95: 65+ | E95: Owner occupier or shared ownership scheme
A96: 95 | B96: Female | D96: 18-64 | E96: Settled mainstream housing with family or friends
A97: 96 | B97: Male | D97: 18-64 | E97: Unknown
A98: 97 | B98: Male | D98: 65+ | E98: Owner occupier or shared ownership scheme
... A123: 122 | B123: Female | D123: 65+ | E123: Tenant: Private landlord
A124: 123 | B124: Male | C124: Autism | D124: 65+ | E124: Tenant: Private landlord
A125: 124 | B125: Female | D125: 18-64 | E125: Owner occupier or shared ownership scheme
A126: 125 | B126: Female | D126: 65+ | E126: Staying with family or friends as a short term guest
A127: 126 | B127: Female | D127: 18-64 | E127: Owner occupier or shared ownership scheme
A128: 127 | B128: Male | D128: 65+ | E128: Owner occupier or shared ownership scheme
A129: 128 | B129: Female | D129: 18-64 | E129: Registered care home
A130: 129 | B130: Male | D130: 65+ | E130: Settled mainstream housing with family or friends
A131: 130 | B131: Female | D131: 18-64 | E131: Owner occupier or shared ownership scheme
A132: 131 | B132: Male | D132: 18-64 | E132: Owner occupier or shared ownership scheme
A133: 132 | B133: Female | D133: 18-64 | E133: Owner occupier or shared ownership scheme
A134: 133 | B134: Male | D134: 18-64 | E134: Tenant: Local authority or other social housing provider
A135: 134 | B135: Female | C135: Dementia | D135: 65+ | E135: Owner occupier or shared ownership scheme
A136: 135 | B136: Female | D136: 18-64 | E136: Settled mainstream housing with family or friends
A137: 136 | B137: Male | D137: 18-64 | E137: Staying with family or friends as a short term guest
A138: 137 | B138: Female | D138: 65+ | E138: Owner occupier or shared ownership scheme
A139: 138 | B139: Male | D139: 18-64 | E139: Owner occupier or shared ownership scheme
A140: 139 | B140: Male | D140: 65+ | E140: Registered care home
A141: 140 | B141: Female | D141: 18-64 | E141: Owner occupier or shared ownership scheme
A142: 141 | B142: Male | D142: 18-64 | E142: Tenant: Local authority or other social housing provider
A143: 142 | B143: Male | D143: 18-64 | E143: Owner occupier or shared ownership scheme
A144: 143 | B144: Male | D144: 65+ | E144: Registered care home
A145: 144 | B145: Female | D145: 18-64 | E145: Registered care home
A146: 145 | B146: Female | D146: 18-64 | E146: Owner occupier or shared ownership scheme
A147: 146 | B147: Male | D147: 65+ | E147: Owner occupier or shared ownership scheme
... A158: 157 | B158: Female | D158: 65+ | E158: Owner occupier or shared ownership scheme
A159: 158 | B159: Female | C159: Autism | D159: 18-64 | E159: Settled mainstream housing with family or friends
A160: 159 | B160: Female | D160: 65+ | E160: Owner occupier or shared ownership scheme
...

Sheet New services table 
A1: Service ID | B1: Person ID | C1: Service Description | D1: Service Class | E1: Start Date | F1: End Date | G1: Service Provider | H1: Earliest Service Date | I1: Is First Service | L1: New People: | M1: =SUBTOTAL(3,B:B) -> 2525
A2: 1 | B2: 1971 | C2: Personal Budget | D2: Long Term | E2: 44840 | F2: 44916 | G2: Green Ltd | H2: =_xlfn.MINIFS(E:E,B:B,B2) -> 44840 | I2: =IF(E2=H2,"Yes","No") -> Yes
A3: 2 | B3: 3823 | C3: Personal Budget | D3: Long Term | E3: 44832 | F3: 45114 | G3: Wells, Levy and Martin | H3: =_xlfn.MINIFS(E:E,B:B,B3) -> 44832 | I3: =IF(E3=H3,"Yes","No") -> Yes
A4: 3 | B4: 2820 | C4: Personal Budget | D4: Long Term | E4: 45057 | G4: Wood Group | H4: =_xlfn.MINIFS(E:E,B:B,B4) -> 45057 | I4: =IF(E4=H4,"Yes","No") -> Yes
A5: 4 | B5: 903 | C5: Equipment | D5: Low level | E5: 44765 | F5: 44953 | G5: Flores-Jones | H5: =_xlfn.MINIFS(E:E,B:B,B5) -> 44765 | I5: =IF(E5=H5,"Yes","No") -> Yes | J5: =SUBTOTAL(9,A5:I5) -> 0
A6: 5 | B6: 365 | C6: Personal Budget | D6: Long Term | E6: 43959 | F6: 44805 | G6: Byrd, Bradford and Jacobs | H6: =_xlfn.MINIFS(E:E,B:B,B6) -> 43959 | I6: =IF(E6=H6,"Yes","No") -> Yes
A7: 6 | B7: 4259 | C7: Nursing Home | D7: Long Term | E7: 44693 | F7: 45440 | G7: Sanders-Moore | H7: =_xlfn.MINIFS(E:E,B:B,B7) -> 44693 | I7: =IF(E7=H7,"Yes","No") -> Yes
A8: 7 | B8: 3120 | C8: Nursing Home | D8: Long Term | E8: 44739 | G8: Montgomery, Lee and Anderson | H8: =_xlfn.MINIFS(E:E,B:B,B8) -> 44739 | I8: =IF(E8=H8,"Yes","No") -> Yes
A9: 8 | B9: 2559 | C9: Residential Home | D9: Long Term | E9: 44731 | F9: 45208 | G9: Wilson, Hernandez and Allen | H9: =_xlfn.MINIFS(E:E,B:B,B9) -> 43725 | I9: =IF(E9=H9,"Yes","No") -> No | J9: =SUBTOTAL(9,A9:I9) -> 0
A10: 9 | B10: 1864 | C10: Direct Payment | D10: Long Term | E10: 44941 | F10: 44969 | G10: Jones, Phillips and Singleton | H10: =_xlfn.MINIFS(E:E,B:B,B10) -> 44941 | I10: =IF(E10=H10,"Yes","No") -> Yes
A11: 10 | B11: 116 | C11: Personal Budget | D11: Long Term | E11: 44898 | G11: Mcguire and Sons | H11: =_xlfn.MINIFS(E:E,B:B,B11) -> 43779 | I11: =IF(E11=H11,"Yes","No") -> No | J11: =SUBTOTAL(9,A11:I11) -> 0
A12: 11 | B12: 2385 | C12: Personal Budget | D12: Long Term | E12: 44467 | F12: 44785 | G12: Parsons-Sexton | H12: =_xlfn.MINIFS(E:E,B:B,B12) -> 44211 | I12: =IF(E12=H12,"Yes","No") -> No | J12: =SUBTOTAL(9,A12:I12) -> 0
A13: 12 | B13: 4977 | C13: Homecare | D13: Long Term | E13: 44891 | F13: 45034 | G13: Martinez Ltd | H13: =_xlfn.MINIFS(E:E,B:B,B13) -> 44523 | I13: =IF(E13=H13,"Yes","No") -> No | J13: =SUBTOTAL(9,A13:I13) -> 0
A14: 13 | B14: 3936 | C14: Equipment | D14: Low level | E14: 45077 | F14: 45307 | G14: Brock LLC | H14: =_xlfn.MINIFS(E:E,B:B,B14) -> 44225 | I14: =IF(E14=H14,"Yes","No") -> No | J14: =SUBTOTAL(9,A14:I14) -> 0
A15: 14 | B15: 4936 | C15: Direct Payment | D15: Long Term | E15: 45096 | F15: 45271 | G15: Cox LLC | H15: =_xlfn.MINIFS(E:E,B:B,B15) -> 44949 | I15: =IF(E15=H15,"Yes","No") -> No | J15: =SUBTOTAL(9,A15:I15) -> 0
A16: 15 | B16: 2491 | C16: Residential Home | D16: Long Term | E16: 45211 | F16: 45362 | G16: White-Murphy | H16: =_xlfn.MINIFS(E:E,B:B,B16) -> 45211 | I16: =IF(E16=H16,"Yes","No") -> Yes
A17: 16 | B17: 943 | C17: Direct Payment | D17: Long Term | E17: 44878 | G17: York, Williams and Young | H17: =_xlfn.MINIFS(E:E,B:B,B17) -> 44878 | I17: =IF(E17=H17,"Yes","No") -> Yes
A18: 17 | B18: 1725 | C18: Personal Budget | D18: Long Term | E18: 45016 | F18: 45325 | G18: Rowe-Price | H18: =_xlfn.MINIFS(E:E,B:B,B18) -> 44220 | I18: =IF(E18=H18,"Yes","No") -> No | J18: =SUBTOTAL(9,A18:I18) -> 0
A19: 18 | B19: 2335 | C19: Homecare | D19: Long Term | E19: 44986 | G19: Dodson PLC | H19: =_xlfn.MINIFS(E:E,B:B,B19) -> 44033 | I19: =IF(E19=H19,"Yes","No") -> No | J19: =SUBTOTAL(9,A19:I19) -> 0
A20: 19 | B20: 2768 | C20: Equipment | D20: Low level | E20: 44629 | F20: 45342 | G20: Carey Ltd | H20: =_xlfn.MINIFS(E:E,B:B,B20) -> 44629 | I20: =IF(E20=H20,"Yes","No") -> Yes | J20: =SUBTOTAL(9,A20:I20) -> 0
A21: 20 | B21: 1138 | C21: Residential Home | D21: Long Term | E21: 45143 | G21: Lamb and Sons | H21: =_xlfn.MINIFS(E:E,B:B,B21) -> 45143 | I21: =IF(E21=H21,"Yes","No") -> Yes
A22: 21 | B22: 2528 | C22: Direct Payment | D22: Long Term | E22: 45308 | F22: 45365 | G22: Kramer, Byrd and Walker | H22: =_xlfn.MINIFS(E:E,B:B,B22) -> 45308 | I22: =IF(E22=H22,"Yes","No") -> Yes
A23: 22 | B23: 4118 | C23: Residential Home | D23: Long Term | E23: 43899 | F23: 44515 | G23: Holloway-Orr | H23: =_xlfn.MINIFS(E:E,B:B,B23) -> 43899 | I23: =IF(E23=H23,"Yes","No") -> Yes
A24: 23 | B24: 3421 | C24: Personal Budget | D24: Long Term | E24: 44530 | F24: 45404 | G24: Mcknight Inc | H24: =_xlfn.MINIFS(E:E,B:B,B24) -> 44530 | I24: =IF(E24=H24,"Yes","No") -> Yes
A25: 24 | B25: 4779 | C25: Residential Home | D25: Long Term | E25: 44187 | F25: 45254 | G25: Rogers, Nichols and Huerta | H25: =_xlfn.MINIFS(E:E,B:B,B25) -> 44187 | I25: =IF(E25=H25,"Yes","No") -> Yes
A26: 25 | B26: 3907 | C26: Homecare | D26: Long Term | E26: 45367 | F26: 45528 | G26: Thornton-Martin | H26: =_xlfn.MINIFS(E:E,B:B,B26) -> 43834 | I26: =IF(E26=H26,"Yes","No") -> No | J26: =SUBTOTAL(9,A26:I26) -> 0
A27: 26 | B27: 3638 | C27: Residential Home | D27: Long Term | E27: 44325 | G27: Vasquez-Thompson | H27: =_xlfn.MINIFS(E:E,B:B,B27) -> 43841 | I27: =IF(E27=H27,"Yes","No") -> No | J27: =SUBTOTAL(9,A27:I27) -> 0
A28: 27 | B28: 2954 | C28: Nursing Home | D28: Long Term | E28: 44221 | G28: Sims-Cohen | H28: =_xlfn.MINIFS(E:E,B:B,B28) -> 44184 | I28: =IF(E28=H28,"Yes","No") -> No | J28: =SUBTOTAL(9,A28:I28) -> 0
A29: 28 | B29: 2368 | C29: Homecare | D29: Long Term | E29: 45289 | F29: 45384 | G29: Williams, Abbott and Goodwin | H29: =_xlfn.MINIFS(E:E,B:B,B29) -> 45289 | I29: =IF(E29=H29,"Yes","No") -> Yes
A30: 29 | B30: 4222 | C30: Direct Payment | D30: Short Term | E30: 45529 | F30: 45532 | G30: Mercado LLC | H30: =_xlfn.MINIFS(E:E,B:B,B30) -> 44849 | I30: =IF(E30=H30,"Yes","No") -> No | J30: =SUBTOTAL(9,A30:I30) -> 0
A31: 30 | B31: 277 | C31: Equipment | D31: Low level | E31: 44200 | F31: 44389 | G31: Smith-Guerrero | H31: =_xlfn.MINIFS(E:E,B:B,B31) -> 44200 | I31: =IF(E31=H31,"Yes","No") -> Yes | J31: =SUBTOTAL(9,A31:I31) -> 0
A32: 31 | B32: 2000 | C32: Equipment | D32: Low level | E32: 44085 | F32: 44304 | G32: Moore-Carlson | H32: =_xlfn.MINIFS(E:E,B:B,B32) -> 44085 | I32: =IF(E32=H32,"Yes","No") -> Yes | J32: =SUBTOTAL(9,A32:I32) -> 0
A33: 32 | B33: 1228 | C33: Personal Budget | D33: Long Term | E33: 45445 | F33: 45513 | G33: Navarro Group | H33: =_xlfn.MINIFS(E:E,B:B,B33) -> 45445 | I33: =IF(E33=H33,"Yes","No") -> Yes
A34: 33 | B34: 3753 | C34: Personal Budget | D34: Long Term | E34: 44365 | F34: 44992 | G34: Williams Group | H34: =_xlfn.MINIFS(E:E,B:B,B34) -> 44365 | I34: =IF(E34=H34,"Yes","No") -> Yes
A35: 34 | B35: 3736 | C35: Nursing Home | D35: Long Term | E35: 44755 | F35: 44997 | G35: Wright-Tucker | H35: =_xlfn.MINIFS(E:E,B:B,B35) -> 43980 | I35: =IF(E35=H35,"Yes","No") -> No | J35: =SUBTOTAL(9,A35:I35) -> 0
A36: 35 | B36: 696 | C36: Direct Payment | D36: Long Term | E36: 44177 | G36: Bautista Ltd | H36: =_xlfn.MINIFS(E:E,B:B,B36) -> 44177 | I36: =IF(E36=H36,"Yes","No") -> Yes
A37: 36 | B37: 1310 | C37: Equipment | D37: Low level | E37: 45112 | F37: 45214 | G37: Harper Group | H37: =_xlfn.MINIFS(E:E,B:B,B37) -> 45112 | I37: =IF(E37=H37,"Yes","No") -> Yes | J37: =SUBTOTAL(9,A37:I37) -> 0
A38: 37 | B38: 4153 | C38: Equipment | D38: Low level | E38: 44344 | F38: 44625 | G38: Bennett, Campos and Sanchez | H38: =_xlfn.MINIFS(E:E,B:B,B38) -> 44344 | I38: =IF(E38=H38,"Yes","No") -> Yes | J38: =SUBTOTAL(9,A38:I38) -> 0
A39: 38 | B39: 3235 | C39: Equipment | D39: Low level | E39: 45290 | F39: 45445 | G39: Perez-Cervantes | H39: =_xlfn.MINIFS(E:E,B:B,B39) -> 44575 | I39: =IF(E39=H39,"Yes","No") -> No | J39: =SUBTOTAL(9,A39:I39) -> 0
A40: 39 | B40: 4115 | C40: Equipment | D40: Low level | E40: 44939 | G40: Griffith PLC | H40: =_xlfn.MINIFS(E:E,B:B,B40) -> 44116 | I40: =IF(E40=H40,"Yes","No") -> No | J40: =SUBTOTAL(9,A40:I40) -> 0
A41: 40 | B41: 2312 | C41: Residential Home | D41: Short Term | E41: 44419 | F41: 44453 | G41: Kaufman LLC | H41: =_xlfn.MINIFS(E:E,B:B,B41) -> 44141 | I41: =IF(E41=H41,"Yes","No") -> No | J41: =SUBTOTAL(9,A41:I41) -> 0
A42: 41 | B42: 2842 | C42: Direct Payment | D42: Long Term | E42: 45074 | F42: 45469 | G42: Murray LLC | H42: =_xlfn.MINIFS(E:E,B:B,B42) -> 44121 | I42: =IF(E42=H42,"Yes","No") -> No | J42: =SUBTOTAL(9,A42:I42) -> 0
A43: 42 | B43: 4209 | C43: Homecare | D43: Long Term | E43: 45032 | G43: Daniels, Rodriguez and Oliver | H43: =_xlfn.MINIFS(E:E,B:B,B43) -> 45032 | I43: =IF(E43=H43,"Yes","No") -> Yes
A44: 43 | B44: 3560 | C44: Homecare | D44: Long Term | E44: 44372 | F44: 45216 | G44: Brown-Smith | H44: =_xlfn.MINIFS(E:E,B:B,B44) -> 44372 | I44: =IF(E44=H44,"Yes","No") -> Yes
A45: 44 | B45: 3399 | C45: Nursing Home | D45: Long Term | E45: 44141 | F45: 45150 | G45: Boyer, Barrera and Williams | H45: =_xlfn.MINIFS(E:E,B:B,B45) -> 43820 | I45: =IF(E45=H45,"Yes","No") -> No | J45: =SUBTOTAL(9,A45:I45) -> 0
A46: 45 | B46: 542 | C46: Residential Home | D46: Long Term | E46: 44999 | F46: 45525 | G46: Romero, Duncan and Williams | H46: =_xlfn.MINIFS(E:E,B:B,B46) -> 44999 | I46: =IF(E46=H46,"Yes","No") -> Yes
A47: 46 | B47: 2695 | C47: Equipment | D47: Low level | E47: 45502 | G47: Moran-Davis | H47: =_xlfn.MINIFS(E:E,B:B,B47) -> 43903 | I47: =IF(E47=H47,"Yes","No") -> No | J47: =SUBTOTAL(9,A47:I47) -> 0
A48: 47 | B48: 4675 | C48: Equipment | D48: Low level | E48: 45490 | F48: 45508 | G48: Carter-Dominguez | H48: =_xlfn.MINIFS(E:E,B:B,B48) -> 44448 | I48: =IF(E48=H48,"Yes","No") -> No | J48: =SUBTOTAL(9,A48:I48) -> 0
A49: 48 | B49: 1089 | C49: Personal Budget | D49: Long Term | E49: 44222 | F49: 44849 | G49: Fuller LLC | H49: =_xlfn.MINIFS(E:E,B:B,B49) -> 44222 | I49: =IF(E49=H49,"Yes","No") -> Yes
A50: 49 | B50: 3364 | C50: Personal Budget | D50: Long Term | E50: 44651 | F50: 45255 | G50: Suarez, Miller and Wright | H50: =_xlfn.MINIFS(E:E,B:B,B50) -> 44651 | I50: =IF(E50=H50,"Yes","No") -> Yes
A51: 50 | B51: 25 | C51: Nursing Home | D51: Long Term | E51: 45433 | G51: Morgan-Mckay | H51: =_xlfn.MINIFS(E:E,B:B,B51) -> 44264 | I51: =IF(E51=H51,"Yes","No") -> No | J51: =SUBTOTAL(9,A51:I51) -> 0
A52: 51 | B52: 1573 | C52: Equipment | D52: Low level | E52: 44147 | G52: Pham, Owens and Ferguson | H52: =_xlfn.MINIFS(E:E,B:B,B52) -> 44147 | I52: =IF(E52=H52,"Yes","No") -> Yes | J52: =SUBTOTAL(9,A52:I52) -> 0
A53: 52 | B53: 2959 | C53: Nursing Home | D53: Long Term | E53: 45249 | F53: 45410 | G53: Booker-Mckinney | H53: =_xlfn.MINIFS(E:E,B:B,B53) -> 45249 | I53: =IF(E53=H53,"Yes","No") -> Yes
A54: 53 | B54: 4237 | C54: Residential Home | D54: Long Term | E54: 45102 | G54: Crane-King | H54: =_xlfn.MINIFS(E:E,B:B,B54) -> 44961 | I54: =IF(E54=H54,"Yes","No") -> No | J54: =SUBTOTAL(9,A54:I54) -> 0
A55: 54 | B55: 1768 | C55: Homecare | D55: Long Term | E55: 44978 | F55: 45253 | G55: Phillips Group | H55: =_xlfn.MINIFS(E:E,B:B,B55) -> 44570 | I55: =IF(E55=H55,"Yes","No") -> No | J55: =SUBTOTAL(9,A55:I55) -> 0
A56: 55 | B56: 4744 | C56: Equipment | D56: Low level | E56: 45088 | F56: 45287 | G56: Baker-Cowan | H56: =_xlfn.MINIFS(E:E,B:B,B56) -> 45088 | I56: =IF(E56=H56,"Yes","No") -> Yes | J56: =SUBTOTAL(9,A56:I56) -> 0
A57: 56 | B57: 2236 | C57: Direct Payment | D57: Long Term | E57: 45387 | F57: 45465 | G57: Lucas and Sons | H57: =_xlfn.MINIFS(E:E,B:B,B57) -> 45161 | I57: =IF(E57=H57,"Yes","No") -> No | J57: =SUBTOTAL(9,A57:I57) -> 0
A58: 57 | B58: 201 | C58: Residential Home | D58: Long Term | E58: 44576 | F58: 45511 | G58: Brennan, Grant and Williams | H58: =_xlfn.MINIFS(E:E,B:B,B58) -> 44576 | I58: =IF(E58=H58,"Yes","No") -> Yes
A59: 58 | B59: 3199 | C59: Equipment | D59: Low level | E59: 45450 | G59: Branch PLC | H59: =_xlfn.MINIFS(E:E,B:B,B59) -> 45450 | I59: =IF(E59=H59,"Yes","No") -> Yes | J59: =SUBTOTAL(9,A59:I59) -> 0
A60: 59 | B60: 257 | C60: Direct Payment | D60: Long Term | E60: 44528 | G60: Williams Ltd | H60: =_xlfn.MINIFS(E:E,B:B,B60) -> 43971 | I60: =IF(E60=H60,"Yes","No") -> No | J60: =SUBTOTAL(9,A60:I60) -> 0
A61: 60 | B61: 3748 | C61: Personal Budget | D61: Long Term | E61: 43822 | G61: Kennedy, Reynolds and Sanchez | H61: =_xlfn.MINIFS(E:E,B:B,B61) -> 43822 | I61: =IF(E61=H61,"Yes","No") -> Yes
A62: 61 | B62: 4643 | C62: Nursing Home | D62: Long Term | E62: 44048 | F62: 45347 | G62: Carpenter, Hicks and Estrada | H62: =_xlfn.MINIFS(E:E,B:B,B62) -> 44048 | I62: =IF(E62=H62,"Yes","No") -> Yes
A63: 62 | B63: 2242 | C63: Personal Budget | D63: Long Term | E63: 43753 | F63: 45106 | G63: Carey, Anderson and Fisher | H63: =_xlfn.MINIFS(E:E,B:B,B63) -> 43753 | I63: =IF(E63=H63,"Yes","No") -> Yes
A64: 63 | B64: 3176 | C64: Homecare | D64: Long Term | E64: 43707 | G64: Mccann Inc | H64: =_xlfn.MINIFS(E:E,B:B,B64) -> 43707 | I64: =IF(E64=H64,"Yes","No") -> Yes
A65: 64 | B65: 3607 | C65: Personal Budget | D65: Long Term | E65: 44895 | F65: 45280 | G65: Miller, Page and Lynn | H65: =_xlfn.MINIFS(E:E,B:B,B65) -> 43756 | I65: =IF(E65=H65,"Yes","No") -> No | J65: =SUBTOTAL(9,A65:I65) -> 0
A66: 65 | B66: 3337 | C66: Equipment | D66: Low level | E66: 43827 | F66: 45039 | G66: Clark-Weber | H66: =_xlfn.MINIFS(E:E,B:B,B66) -> 43827 | I66: =IF(E66=H66,"Yes","No") -> Yes | J66: =SUBTOTAL(9,A66:I66) -> 0
A67: 66 | B67: 4898 | C67: Direct Payment | D67: Long Term | E67: 45197 | F67: 45254 | G67: Oconnor Group | H67: =_xlfn.MINIFS(E:E,B:B,B67) -> 44493 | I67: =IF(E67=H67,"Yes","No") -> No | J67: =SUBTOTAL(9,A67:I67) -> 0
A68: 67 | B68: 414 | C68: Personal Budget | D68: Long Term | E68: 44599 | G68: Acosta, Roberts and Rivera | H68: =_xlfn.MINIFS(E:E,B:B,B68) -> 44537 | I68: =IF(E68=H68,"Yes","No") -> No | J68: =SUBTOTAL(9,A68:I68) -> 0
A69: 68 | B69: 2015 | C69: Equipment | D69: Low level | E69: 44241 | F69: 44273 | G69: Perez, Thomas and Moore | H69: =_xlfn.MINIFS(E:E,B:B,B69) -> 44241 | I69: =IF(E69=H69,"Yes","No") -> Yes | J69: =SUBTOTAL(9,A69:I69) -> 0
A70: 69 | B70: 1382 | C70: Homecare | D70: Long Term | E70: 45237 | G70: Weaver, Whitehead and Carter | H70: =_xlfn.MINIFS(E:E,B:B,B70) -> 45167 | I70: =IF(E70=H70,"Yes","No") -> No | J70: =SUBTOTAL(9,A70:I70) -> 0
A71: 70 | B71: 1099 | C71: Direct Payment | D71: Long Term | E71: 45464 | F71: 45475 | G71: Floyd, Love and Weber | H71: =_xlfn.MINIFS(E:E,B:B,B71) -> 43741 | I71: =IF(E71=H71,"Yes","No") -> No | J71: =SUBTOTAL(9,A71:I71) -> 0
A72: 71 | B72: 3427 | C72: Personal Budget | D72: Long Term | E72: 44973 | F72: 45149 | G72: Smith LLC | H72: =_xlfn.MINIFS(E:E,B:B,B72) -> 43792 | I72: =IF(E72=H72,"Yes","No") -> No | J72: =SUBTOTAL(9,A72:I72) -> 0
A73: 72 | B73: 3656 | C73: Nursing Home | D73: Long Term | E73: 44206 | F73: 44265 | G73: Kennedy and Sons | H73: =_xlfn.MINIFS(E:E,B:B,B73) -> 44206 | I73: =IF(E73=H73,"Yes","No") -> Yes
A74: 73 | B74: 910 | C74: Nursing Home | D74: Long Term | E74: 45158 | F74: 45354 | G74: Williams-Cooper | H74: =_xlfn.MINIFS(E:E,B:B,B74) -> 45158 | I74: =IF(E74=H74,"Yes","No") -> Yes
A75: 74 | B75: 188 | C75: Direct Payment | D75: Long Term | E75: 45105 | F75: 45280 | G75: Woodward-Huber | H75: =_xlfn.MINIFS(E:E,B:B,B75) -> 45105 | I75: =IF(E75=H75,"Yes","No") -> Yes
A76: 75 | B76: 4045 | C76: Nursing Home | D76: Long Term | E76: 45417 | F76: 45526 | G76: Herrera, Martin and Gibson | H76: =_xlfn.MINIFS(E:E,B:B,B76) -> 43725 | I76: =IF(E76=H76,"Yes","No") -> No | J76: =SUBTOTAL(9,A76:I76) -> 0
A77: 76 | B77: 3757 | C77: Personal Budget | D77: Long Term | E77: 44312 | G77: Nunez Inc | H77: =_xlfn.MINIFS(E:E,B:B,B77) -> 44312 | I77: =IF(E77=H77,"Yes","No") -> Yes
A78: 77 | B78: 2016 | C78: Personal Budget | D78: Long Term | E78: 44694 | F78: 44886 | G78: Marshall Group | H78: =_xlfn.MINIFS(E:E,B:B,B78) -> 44694 | I78: =IF(E78=H78,"Yes","No") -> Yes
A79: 78 | B79: 2093 | C79: Direct Payment | D79: Long Term | E79: 43751 | F79: 45089 | G79: Bryant, Lopez and Thompson | H79: =_xlfn.MINIFS(E:E,B:B,B79) -> 43751 | I79: =IF(E79=H79,"Yes","No") -> Yes
A80: 79 | B80: 3645 | C80: Personal Budget | D80: Long Term | E80: 44067 | F80: 45331 | G80: Martin LLC | H80: =_xlfn.MINIFS(E:E,B:B,B80) -> 44067 | I80: =IF(E80=H80,"Yes","No") -> Yes
A81: 80 | B81: 2131 | C81: Equipment | D81: Low level | E81: 44546 | F81: 45415 | G81: Carlson-Little | H81: =_xlfn.MINIFS(E:E,B:B,B81) -> 44546 | I81: =IF(E81=H81,"Yes","No") -> Yes | J81: =SUBTOTAL(9,A81:I81) -> 0
A82: 81 | B82: 358 | C82: Homecare | D82: Long Term | E82: 45093 | F82: 45489 | G82: Glass Ltd | H82: =_xlfn.MINIFS(E:E,B:B,B82) -> 45093 | I82: =IF(E82=H82,"Yes","No") -> Yes
A83: 82 | B83: 2423 | C83: Nursing Home | D83: Long Term | E83: 44894 | G83: Compton Ltd | H83: =_xlfn.MINIFS(E:E,B:B,B83) -> 44894 | I83: =IF(E83=H83,"Yes","No") -> Yes
A84: 83 | B84: 4258 | C84: Equipment | D84: Low level | E84: 44672 | F84: 45213 | G84: Smith-Perry | H84: =_xlfn.MINIFS(E:E,B:B,B84) -> 44672 | I84: =IF(E84=H84,"Yes","No") -> Yes | J84: =SUBTOTAL(9,A84:I84) -> 0
A85: 84 | B85: 4546 | C85: Direct Payment | D85: Long Term | E85: 45120 | G85: Adams, Smith and Coleman | H85: =_xlfn.MINIFS(E:E,B:B,B85) -> 44152 | I85: =IF(E85=H85,"Yes","No") -> No | J85: =SUBTOTAL(9,A85:I85) -> 0
A86: 85 | B86: 1498 | C86: Nursing Home | D86: Long Term | E86: 44470 | F86: 45328 | G86: Jones-Cantu | H86: =_xlfn.MINIFS(E:E,B:B,B86) -> 44241 | I86: =IF(E86=H86,"Yes","No") -> No | J86: =SUBTOTAL(9,A86:I86) -> 0
A87: 86 | B87: 2159 | C87: Equipment | D87: Low level | E87: 45305 | G87: West-Stevens | H87: =_xlfn.MINIFS(E:E,B:B,B87) -> 44246 | I87: =IF(E87=H87,"Yes","No") -> No | J87: =SUBTOTAL(9,A87:I87) -> 0
A88: 87 | B88: 2556 | C88: Personal Budget | D88: Long Term | E88: 43834 | F88: 44248 | G88: Stewart, Johnson and Johnson | H88: =_xlfn.MINIFS(E:E,B:B,B88) -> 43834 | I88: =IF(E88=H88,"Yes","No") -> Yes
A89: 88 | B89: 2343 | C89: Direct Payment | D89: Long Term | E89: 44684 | F89: 44722 | G89: Ross Ltd | H89: =_xlfn.MINIFS(E:E,B:B,B89) -> 44684 | I89: =IF(E89=H89,"Yes","No") -> Yes
A90: 89 | B90: 2952 | C90: Direct Payment | D90: Long Term | E90: 44529 | F90: 44543 | G90: Walker LLC | H90: =_xlfn.MINIFS(E:E,B:B,B90) -> 44529 | I90: =IF(E90=H90,"Yes","No") -> Yes
A91: 90 | B91: 1239 | C91: Nursing Home | D91: Long Term | E91: 44339 | F91: 44631 | G91: Petersen, Moore and Spencer | H91: =_xlfn.MINIFS(E:E,B:B,B91) -> 44339 | I91: =IF(E91=H91,"Yes","No") -> Yes
A92: 91 | B92: 974 | C92: Personal Budget | D92: Short Term | E92: 45113 | F92: 45119 | G92: Williams LLC | H92: =_xlfn.MINIFS(E:E,B:B,B92) -> 45113 | I92: =IF(E92=H92,"Yes","No") -> Yes | J92: =SUBTOTAL(9,A92:I92) -> 0
A93: 92 | B93: 4728 | C93: Nursing Home | D93: Long Term | E93: 44622 | G93: Smith and Sons | H93: =_xlfn.MINIFS(E:E,B:B,B93) -> 44312 | I93: =IF(E93=H93,"Yes","No") -> No | J93: =SUBTOTAL(9,A93:I93) -> 0
A94: 93 | B94: 3966 | C94: Residential Home | D94: Long Term | E94: 44119 | G94: Miller-Garcia | H94: =_xlfn.MINIFS(E:E,B:B,B94) -> 44119 | I94: =IF(E94=H94,"Yes","No") -> Yes
A95: 94 | B95: 1051 | C95: Equipment | D95: Low level | E95: 43990 | F95: 44589 | G95: Nguyen, Johnson and Ramos | H95: =_xlfn.MINIFS(E:E,B:B,B95) -> 43990 | I95: =IF(E95=H95,"Yes","No") -> Yes | J95: =SUBTOTAL(9,A95:I95) -> 0
A96: 95 | B96: 3702 | C96: Residential Home | D96: Long Term | E96: 44175 | F96: 44569 | G96: Ferguson Inc | H96: =_xlfn.MINIFS(E:E,B:B,B96) -> 44175 | I96: =IF(E96=H96,"Yes","No") -> Yes
A97: 96 | B97: 2781 | C97: Equipment | D97: Low level | E97: 44865 | F97: 45531 | G97: Blankenship LLC | H97: =_xlfn.MINIFS(E:E,B:B,B97) -> 43748 | I97: =IF(E97=H97,"Yes","No") -> No | J97: =SUBTOTAL(9,A97:I97) -> 0
A98: 97 | B98: 1589 | C98: Homecare | D98: Long Term | E98: 45120 | F98: 45191 | G98: Smith, Perez and Miller | H98: =_xlfn.MINIFS(E:E,B:B,B98) -> 45120 | I98: =IF(E98=H98,"Yes","No") -> Yes
A99: 98 | B99: 3879 | C99: Direct Payment | D99: Long Term | E99: 45367 | F99: 45524 | G99: Hernandez, Perez and Harmon | H99: =_xlfn.MINIFS(E:E,B:B,B99) -> 44198 | I99: =IF(E99=H99,"Yes","No") -> No | J99: =SUBTOTAL(9,A99:I99) -> 0
A100: 99 | B100: 2369 | C100: Nursing Home | D100: Long Term | E100: 45379 | F100: 45445 | G100: Haney PLC | H100: =_xlfn.MINIFS(E:E,B:B,B100) -> 45379 | I100: =IF(E100=H100,"Yes","No") -> Yes
...

Sheet New assessments completed
A1: Person ID | B1: Event | C1: Assessment start | D1: Assessment end | E1: Support Date
A2: 1687 | B2: Assessment | C2: 45017 | D2: 45023 | E2: =D2-C2 -> 6
A3: 2116 | B3: Assessment | C3: 45017 | D3: 45022 | E3: =D3-C3 -> 5
A4: 2820 | B4: Assessment | C4: 45017 | D4: 45022 | E4: =D4-C4 -> 5
A5: 3514 | B5: Assessment | C5: 45017 | D5: 45022 | E5: =D5-C5 -> 5
A6: 3730 | B6: Assessment | C6: 45017 | D6: 45023 | E6: =D6-C6 -> 6
A7: 508 | B7: Assessment | C7: 45018 | D7: 45023 | E7: =D7-C7 -> 5
A8: 517 | B8: Assessment | C8: 45018 | D8: 45023 | E8: =D8-C8 -> 5
A9: 4209 | B9: Assessment | C9: 45019 | D9: 45025 | E9: =D9-C9 -> 6
A10: 2549 | B10: Assessment | C10: 45020 | D10: 45025 | E10: =D10-C10 -> 5
A11: 2750 | B11: Assessment | C11: 45020 | D11: 45025 | E11: =D11-C11 -> 5
A12: 446 | B12: Assessment | C12: 45021 | D12: 45026 | E12: =D12-C12 -> 5
A13: 2557 | B13: Assessment | C13: 45021 | D13: 45026 | E13: =D13-C13 -> 5
... A1089: 787 | B1089: Assessment | C1089: 45527 | D1089: 45537 | E1089: =D1089-C1089 -> 10

Sheet New People Info
A1: Person ID | B1: Gender | C1: Health condition | D1: Age band | E1: Accommodation status | F1: Row Labels | G1: Sum of Person ID | I1: Person ID | J1: Gender | K1: Health Condition | L1: Age | M1: Accomodation Status
A2: 1 | B2: Male | D2: 65+ | E2: Tenant: Private landlord | F2: ASD | G2: 4312 | I2: {=_xlfn._xlws.FILTER(A2:E100, (C2:C100="Autism") + (C2:C100="ASD"), "No results found")} -> 10 | J2: Male | K2: ASD | L2: 18-64 | M2: Tenant: Private landlord
A3: 2 | B3: Female | D3: 18-64 | E3: Tenant: Private landlord | F3: 18-64 | G3: 4312 | I3: 13 | J3: Male | K3: Autism | L3: 18-64 | M3: Registered care home
A4: 3 | B4: Female | D4: 18-64 | E4: Unknown | F4: Female | G4: 2690 | I4: 32 | J4: Male | K4: Autism | L4: 18-64 | M4: Tenant: Private landlord
A5: 4 | B5: Male | D5: 18-64 | E5: Tenant: Private landlord | F5: Male | G5: 1622 | I5: 85 | J5: Male | K5: Autism | L5: 18-64 | M5: Settled mainstream housing with family or friends
A6: 5 | B6: Male | D6: 18-64 | E6: Registered care home | F6: Autism | G6: 19727
A7: 6 | B7: Female | D7: 65+ | E7: Tenant: Private landlord | F7: 18-64 | G7: 19178
A8: 7 | B8: Male | D8: 18-64 | E8: Tenant: Local authority or other social housing provider | F8: Female | G8: 7177
A9: 8 | B9: Female | C9: Dementia | D9: 65+ | E9: Tenant: Private landlord | F9: Male | G9: 12001
A10: 9 | B10: Male | D10: 65+ | E10: Tenant: Private landlord | F10: 65+ | G10: 549
A11: 10 | B11: Male | C11: ASD | D11: 18-64 | E11: Tenant: Private landlord | F11: Female | G11: 426
A12: 11 | B12: Male | D12: 18-64 | E12: Tenant: Private landlord | F12: Male | G12: 123
A13: 12 | B13: Male | D13: 18-64 | E13: Tenant: Private landlord | F13: Blind/severely sight impaired | G13: 15892
A14: 13 | B14: Male | C14: Autism | D14: 18-64 | E14: Registered care home | F14: 18-64 | G14: 5907
A15: 14 | B15: Male | D15: 65+ | E15: Unknown | F15: Female | G15: 5858
A16: 15 | B16: Female | D16: 18-64 | E16: Tenant: Private landlord | F16: Male | G16: 49
A17: 16 | B17: Female | D17: 65+ | E17: Registered care home | F17: 65+ | G17: 9985
A18: 17 | B18: Male | D18: 18-64 | E18: Registered care home | F18: Female | G18: 4996
A19: 18 | B19: Male | D19: 18-64 | E19: Tenant: Private landlord | F19: Male | G19: 4989
A20: 19 | B20: Female | D20: 65+ | E20: Tenant: Private landlord | F20: Dementia | G20: 15415
A21: 20 | B21: Female | D21: 18-64 | E21: Unknown | F21: 65+ | G21: 15415
A22: 21 | B22: Female | D22: 18-64 | E22: Registered care home | F22: Female | G22: 4994
A23: 22 | B23: Male | D23: 18-64 | E23: Tenant: Private landlord | F23: Male | G23: 10421
A24: 23 | B24: Male | D24: 18-64 | E24: Tenant: Private landlord | F24: Partial sight/sight impaired | G24: 8850
A25: 24 | B25: Female | D25: 18-64 | E25: Tenant: Private landlord | F25: 18-64 | G25: 33
A26: 25 | B26: Male | D26: 65+ | E26: Tenant: Private landlord | F26: Female | G26: 33
... A29: 28 | B29: Female | D29: 65+ | E29: Tenant: Private landlord | F29: Male | G29: 8641
A30: 29 | B30: Male | C30: Dementia | D30: 65+ | E30: Unknown | F30: Grand Total | G30: 64196
A31: 30 | B31: Female | D31: 18-64 | E31: Tenant: Private landlord
A32: 31 | B32: Female | D32: 18-64 | E32: Tenant: Local authority or other social housing provider
A33: 32 | B33: Male | C33: Autism | D33: 18-64 | E33: Tenant: Private landlord
A34: 33 | B34: Female | C34: Partial sight/sight impaired | D34: 18-64 | E34: Registered care home
A35: 34 | B35: Female | D35: 18-64 | E35: Tenant: Private landlord
A36: 35 | B36: Female | D36: 65+ | E36: Tenant: Private landlord
A37: 36 | B37: Female | D37: 65+ | E37: Tenant: Private landlord
A38: 37 | B38: Male | D38: 65+ | E38: Tenant: Private landlord
A39: 38 | B39: Female | D39: 18-64 | E39: Unknown
A40: 39 | B40: Male | D40: 18-64 | E40: Tenant: Private landlord
A41: 40 | B41: Female | D41: 65+ | E41: Tenant: Private landlord
A42: 41 | B42: Female | D42: 65+ | E42: Unknown
A43: 42 | B43: Male | D43: 65+ | E43: Unknown
A44: 43 | B44: Female | D44: 18-64 | E44: Registered care home
A45: 44 | B45: Male | D45: 18-64 | E45: Registered care home
A46: 45 | B46: Female | D46: 18-64 | E46: Tenant: Private landlord
... A49: 48 | B49: Female | D49: 18-64 | E49: Tenant: Private landlord
A50: 49 | B50: Male | C50: Blind/severely sight impaired | D50: 18-64 | E50: Registered nursing home
A51: 50 | B51: Female | D51: 18-64 | E51: Registered care home
A52: 51 | B52: Female | D52: 18-64 | E52: Tenant: Private landlord
A53: 52 | B53: Female | D53: 18-64 | E53: Tenant: Private landlord
A54: 53 | B54: Female | D54: 18-64 | E54: Unknown
A55: 54 | B55: Male | D55: 18-64 | E55: Tenant: Private landlord
A56: 55 | B56: Female | D56: 65+ | E56: Tenant: Private landlord
A57: 56 | B57: Male | D57: 18-64 | E57: Tenant: Private landlord
A58: 57 | B58: Female | D58: 65+ | E58: Tenant: Private landlord
A59: 58 | B59: Male | D59: 18-64 | E59: Tenant: Local authority or other social housing provider
A60: 59 | B60: Female | D60: 65+ | E60: Tenant: Private landlord
A61: 60 | B61: Male | D61: 18-64 | E61: Tenant: Private landlord
A62: 61 | B62: Female | D62: 18-64 | E62: Tenant: Private landlord
... A85: 84 | B85: Female | D85: 65+ | E85: Registered care home
A86: 85 | B86: Male | C86: Autism | D86: 18-64 | E86: Settled mainstream housing with family or friends
A87: 86 | B87: Female | D87: 18-64 | E87: Tenant: Local authority or other social housing provider
A88: 87 | B88: Male | D88: 65+ | E88: Sheltered housing
A89: 88 | B89: Female | D89: 18-64 | E89: Owner occupier or shared ownership scheme
A90: 89 | B90: Male | D90: 18-64 | E90: Owner occupier or shared ownership scheme
A91: 90 | B91: Female | D91: 65+ | E91: Registered care home
A92: 91 | B92: Female | D92: 18-64 | E92: Registered care home
A93: 92 | B93: Male | D93: 18-64 | E93: Owner occupier or shared ownership scheme
A94: 93 | B94: Male | D94: 65+ | E94: Staying with family or friends as a short term guest
A95: 94 | B95: Female | D95: 65+ | E95: Owner occupier or shared ownership scheme
A96: 95 | B96: Female | D96: 18-64 | E96: Settled mainstream housing with family or friends
A97: 96 | B97: Male | D97: 18-64 | E97: Unknown
A98: 97 | B98: Male | D98: 65+ | E98: Owner occupier or shared ownership scheme
... A123: 122 | B123: Female | D123: 65+ | E123: Tenant: Private landlord
A124: 123 | B124: Male | C124: Autism | D124: 65+ | E124: Tenant: Private landlord
A125: 124 | B125: Female | D125: 18-64 | E125: Owner occupier or shared ownership scheme
A126: 125 | B126: Female | D126: 65+ | E126: Staying with family or friends as a short term guest
A127: 126 | B127: Female | D127: 18-64 | E127: Owner occupier or shared ownership scheme
A128: 127 | B128: Male | D128: 65+ | E128: Owner occupier or shared ownership scheme
A129: 128 | B129: Female | D129: 18-64 | E129: Registered care home
A130: 129 | B130: Male | D130: 65+ | E130: Settled mainstream housing with family or friends
A131: 130 | B131: Female | D131: 18-64 | E131: Owner occupier or shared ownership scheme
A132: 131 | B132: Male | D132: 18-64 | E132: Owner occupier or shared ownership scheme
A133: 132 | B133: Female | D133: 18-64 | E133: Owner occupier or shared ownership scheme
A134: 133 | B134: Male | D134: 18-64 | E134: Tenant: Local authority or other social housing provider
A135: 134 | B135: Female | C135: Dementia | D135: 65+ | E135: Owner occupier or shared ownership scheme
A136: 135 | B136: Female | D136: 18-64 | E136: Settled mainstream housing with family or friends
A137: 136 | B137: Male | D137: 18-64 | E137: Staying with family or friends as a short term guest
A138: 137 | B138: Female | D138: 65+ | E138: Owner occupier or shared ownership scheme
A139: 138 | B139: Male | D139: 18-64 | E139: Owner occupier or shared ownership scheme
A140: 139 | B140: Male | D140: 65+ | E140: Registered care home
A141: 140 | B141: Female | D141: 18-64 | E141: Owner occupier or shared ownership scheme
A142: 141 | B142: Male | D142: 18-64 | E142: Tenant: Local authority or other social housing provider
A143: 142 | B143: Male | D143: 18-64 | E143: Owner occupier or shared ownership scheme
A144: 143 | B144: Male | D144: 65+ | E144: Registered care home
A145: 144 | B145: Female | D145: 18-64 | E145: Registered care home
A146: 145 | B146: Female | D146: 18-64 | E146: Owner occupier or shared ownership scheme
A147: 146 | B147: Male | D147: 65+ | E147: Owner occupier or shared ownership scheme
... A158: 157 | B158: Female | D158: 65+ | E158: Owner occupier or shared ownership scheme
A159: 158 | B159: Female | C159: Autism | D159: 18-64 | E159: Settled mainstream housing with family or friends
A160: 159 | B160: Female | D160: 65+ | E160: Owner occupier or shared ownership scheme
...

Sheet Dashboard 1
A1: New People
A2: Service ID | B2: Person ID | C2: Health Condition | D2: Service Description | E2: Service Class | F2: Start Date | G2: End Date | H2: Service Provider | I2: Earliest Service Date | J2: Is First Service | K2: Month Started | M2: New People: | N2: =SUBTOTAL(3,B:B) -> 3937 | P2: Row Labels | Q2: Sum of Person ID
A3: 1 | B3: 1971 | D3: Personal Budget | E3: Long Term | F3: 44840 | G3: 44916 | H3: Green Ltd | I3: =_xlfn.MINIFS(F:F,B:B,B3) -> 44840 | J3: =IF(F3=I3,"True","False") -> True | K3: =TEXT(F1,"mmm-yyyy") -> Jan-1900 | P3: Apr-2020 | Q3: 121260
A4: 2 | B4: 3823 | D4: Personal Budget | E4: Long Term | F4: 44832 | G4: 45114 | H4: Wells, Levy and Martin | I4: =_xlfn.MINIFS(F:F,B:B,B4) -> 44832 | J4: =IF(F4=I4,"True","False") -> True | K4: =TEXT(F2,"mmm-yyyy") -> Start Date | P4: Apr-2021 | Q4: 171766
A5: 3 | B5: 2820 | C5: =_xlfn.XLOOKUP(A3,'New People Info'!A:A,'New People Info'!C:C) -> 0 | D5: Personal Budget | E5: Long Term | F5: 45057 | H5: Wood Group | I5: =_xlfn.MINIFS(F:F,B:B,B5) -> 45057 | J5: =IF(F5=I5,"True","False") -> True | K5: =TEXT(F3,"mmm-yyyy") -> Oct-2022 | P5: Apr-2022 | Q5: 175667
A6: 4 | B6: 903 | D6: Equipment | E6: Low level | F6: 44765 | G6: 44953 | H6: Flores-Jones | I6: =_xlfn.MINIFS(F:F,B:B,B6) -> 44765 | J6: =IF(F6=I6,"Yes","No") -> Yes | P6: Apr-2023 | Q6: 203213
A7: 5 | B7: 365 | D7: Personal Budget | E7: Long Term | F7: 43959 | G7: 44805 | H7: Byrd, Bradford and Jacobs | I7: =_xlfn.MINIFS(F:F,B:B,B7) -> 43959 | J7: =IF(F7=I7,"True","False") -> True | K7: =TEXT(F5,"mmm-yyyy") -> May-2023 | P7: Apr-2024 | Q7: 136263
A8: 6 | B8: 4259 | D8: Nursing Home | E8: Long Term | F8: 44693 | G8: 45440 | H8: Sanders-Moore | I8: =_xlfn.MINIFS(F:F,B:B,B8) -> 44693 | J8: =IF(F8=I8,"True","False") -> True | K8: =TEXT(F6,"mmm-yyyy") -> Jul-2022 | P8: Aug-2019 | Q8: 13602
A9: 7 | B9: 3120 | D9: Nursing Home | E9: Long Term | F9: 44739 | H9: Montgomery, Lee and Anderson | I9: =_xlfn.MINIFS(F:F,B:B,B9) -> 44739 | J9: =IF(F9=I9,"True","False") -> True | K9: =TEXT(F7,"mmm-yyyy") -> May-2020 | P9: Aug-2020 | Q9: 216676
A10: 8 | B10: 2559 | D10: Residential Home | E10: Long Term | F10: 44731 | G10: 45208 | H10: Wilson, Hernandez and Allen | I10: =_xlfn.MINIFS(F:F,B:B,B10) -> 43725 | J10: =IF(F10=I10,"True","False") -> False | K10: =TEXT(F8,"mmm-yyyy") -> May-2022 | P10: Aug-2021 | Q10: 175939
A11: 9 | B11: 1864 | D11: Direct Payment | E11: Long Term | F11: 44941 | G11: 44969 | H11: Jones, Phillips and Singleton | I11: =_xlfn.MINIFS(F:F,B:B,B11) -> 44941 | J11: =IF(F11=I11,"True","False") -> True | K11: =TEXT(F9,"mmm-yyyy") -> Jun-2022 | P11: Aug-2022 | Q11: 147030
A12: 10 | B12: 116 | D12: Personal Budget | E12: Long Term | F12: 44898 | H12: Mcguire and Sons | I12: =_xlfn.MINIFS(F:F,B:B,B12) -> 43779 | J12: =IF(F12=I12,"True","False") -> False | K12: =TEXT(F10,"mmm-yyyy") -> Jun-2022 | P12: Aug-2023 | Q12: 176620
A13: 11 | B13: 2385 | D13: Personal Budget | E13: Long Term | F13: 44467 | G13: 44785 | H13: Parsons-Sexton | I13: =_xlfn.MINIFS(F:F,B:B,B13) -> 44211 | J13: =IF(F13=I13,"True","False") -> False | K13: =TEXT(F11,"mmm-yyyy") -> Jan-2023 | P13: Aug-2024 | Q13: 184465
A14: 12 | B14: 4977 | D14: Homecare | E14: Long Term | F14: 44891 | G14: 45034 | H14: Martinez Ltd | I14: =_xlfn.MINIFS(F:F,B:B,B14) -> 44523 | J14: =IF(F14=I14,"True","False") -> False | K14: =TEXT(F12,"mmm-yyyy") -> Dec-2022 | P14: Dec-2019 | Q14: 129272
A15: 13 | B15: 3936 | D15: Equipment | E15: Low level | F15: 45077 | G15: 45307 | H15: Brock LLC | I15: =_xlfn.MINIFS(F:F,B:B,B15) -> 44225 | J15: =IF(F15=I15,"Yes","No") -> No | P15: Dec-2020 | Q15: 199933
A16: 14 | B16: 4936 | C16: =_xlfn.XLOOKUP(A14,'New People Info'!A:A,'New People Info'!C:C) -> 0 | D16: Direct Payment | E16: Long Term | F16: 45096 | G16: 45271 | H16: Cox LLC | I16: =_xlfn.MINIFS(F:F,B:B,B16) -> 44949 | J16: =IF(F16=I16,"True","False") -> False | K16: =TEXT(F14,"mmm-yyyy") -> Nov-2022 | M16: Number of new people who have Autism | N16: =COUNTIF(C:C,"Autism") -> 3 | P16: Dec-2021 | Q16: 162050
A17: 15 | B17: 2491 | C17: =_xlfn.XLOOKUP(A15,'New People Info'!A:A,'New People Info'!C:C) -> Autism | D17: Residential Home | E17: Long Term | F17: 45211 | G17: 45362 | H17: White-Murphy | I17: =_xlfn.MINIFS(F:F,B:B,B17) -> 45211 | J17: =IF(F17=I17,"True","False") -> True | K17: =TEXT(F15,"mmm-yyyy") -> May-2023 | P17: Dec-2022 | Q17: 170066
A18: 16 | B18: 943 | D18: Direct Payment | E18: Long Term | F18: 44878 | H18: York, Williams and Young | I18: =_xlfn.MINIFS(F:F,B:B,B18) -> 44878 | J18: =IF(F18=I18,"True","False") -> True | K18: =TEXT(F16,"mmm-yyyy") -> Jun-2023 | P18: Dec-2023 | Q18: 168758
A19: 17 | B19: 1725 | D19: Personal Budget | E19: Long Term | F19: 45016 | G19: 45325 | H19: Rowe-Price | I19: =_xlfn.MINIFS(F:F,B:B,B19) -> 44220 | J19: =IF(F19=I19,"True","False") -> False | K19: =TEXT(F17,"mmm-yyyy") -> Oct-2023 | P19: Feb-2020 | Q19: 152848
A20: 18 | B20: 2335 | D20: Homecare | E20: Long Term | F20: 44986 | H20: Dodson PLC | I20: =_xlfn.MINIFS(F:F,B:B,B20) -> 44033 | J20: =IF(F20=I20,"True","False") -> False | K20: =TEXT(F18,"mmm-yyyy") -> Nov-2022 | P20: Feb-2021 | Q20: 192076
A21: 19 | B21: 2768 | D21: Equipment | E21: Low level | F21: 44629 | G21: 45342 | H21: Carey Ltd | I21: =_xlfn.MINIFS(F:F,B:B,B21) -> 44629 | J21: =IF(F21=I21,"Yes","No") -> Yes | P21: Feb-2022 | Q21: 156308
A22: 20 | B22: 1138 | C22: =_xlfn.XLOOKUP(A20,'New People Info'!A:A,'New People Info'!C:C) -> 0 | D22: Residential Home | E22: Long Term | F22: 45143 | H22: Lamb and Sons | I22: =_xlfn.MINIFS(F:F,B:B,B22) -> 45143 | J22: =IF(F22=I22,"True","False") -> True | K22: =TEXT(F20,"mmm-yyyy") -> Mar-2023 | P22: Feb-2023 | Q22: 134005
A23: 21 | B23: 2528 | C23: =_xlfn.XLOOKUP(A21,'New People Info'!A:A,'New People Info'!C:C) -> 0 | D23: Direct Payment | E23: Long Term | F23: 45308 | G23: 45365 | H23: Kramer, Byrd and Walker | I23: =_xlfn.MINIFS(F:F,B:B,B23) -> 45308 | J23: =IF(F23=I23,"True","False") -> True | K23: =TEXT(F21,"mmm-yyyy") -> Mar-2022 | P23: Feb-2024 | Q23: 136394
A24: 22 | B24: 4118 | D24: Residential Home | E24: Long Term | F24: 43899 | G24: 44515 | H24: Holloway-Orr | I24: =_xlfn.MINIFS(F:F,B:B,B24) -> 43899 | J24: =IF(F24=I24,"True","False") -> True | K24: =TEXT(F22,"mmm-yyyy") -> Aug-2023 | P24: Jan-1900 | Q24: 1971
A25: 23 | B25: 3421 | D25: Personal Budget | E25: Long Term | F25: 44530 | G25: 45404 | H25: Mcknight Inc | I25: =_xlfn.MINIFS(F:F,B:B,B25) -> 44530 | J25: =IF(F25=I25,"True","False") -> True | K25: =TEXT(F23,"mmm-yyyy") -> Jan-2024 | P25: Jan-2020 | Q25: 162206
A26: 24 | B26: 4779 | D26: Residential Home | E26: Long Term | F26: 44187 | G26: 45254 | H26: Rogers, Nichols and Huerta | I26: =_xlfn.MINIFS(F:F,B:B,B26) -> 44187 | J26: =IF(F26=I26,"True","False") -> True | K26: =TEXT(F24,"mmm-yyyy") -> Mar-2020 | P26: Jan-2021 | Q26: 185855
A27: 25 | B27: 3907 | C27: =_xlfn.XLOOKUP(A25,'New People Info'!A:A,'New People Info'!C:C) -> 0 | D27: Homecare | E27: Long Term | F27: 45367 | G27: 45528 | H27: Thornton-Martin | I27: =_xlfn.MINIFS(F:F,B:B,B27) -> 43834 | J27: =IF(F27=I27,"True","False") -> False | K27: =TEXT(F25,"mmm-yyyy") -> Nov-2021 | P27: Jan-2022 | Q27: 167895
A28: 26 | B28: 3638 | D28: Residential Home | E28: Long Term | F28: 44325 | H28: Vasquez-Thompson | I28: =_xlfn.MINIFS(F:F,B:B,B28) -> 43841 | J28: =IF(F28=I28,"True","False") -> False | K28: =TEXT(F26,"mmm-yyyy") -> Dec-2020 | P28: Jan-2023 | Q28: 150711
A29: 27 | B29: 2954 | D29: Nursing Home | E29: Long Term | F29: 44221 | H29: Sims-Cohen | I29: =_xlfn.MINIFS(F:F,B:B,B29) -> 44184 | J29: =IF(F29=I29,"True","False") -> False | K29: =TEXT(F27,"mmm-yyyy") -> Mar-2024 | P29: Jan-2024 | Q29: 143217
A30: 28 | B30: 2368 | C30: =_xlfn.XLOOKUP(A28,'New People Info'!A:A,'New People Info'!C:C) -> 0 | D30: Homecare | E30: Long Term | F30: 45289 | G30: 45384 | H30: Williams, Abbott and Goodwin | I30: =_xlfn.MINIFS(F:F,B:B,B30) -> 45289 | J30: =IF(F30=I30,"True","False") -> True | K30: =TEXT(F28,"mmm-yyyy") -> May-2021 | P30: Jul-2020 | Q30: 153189
A31: 29 | B31: 4222 | D31: Direct Payment | E31: Short Term | F31: 45529 | G31: 45532 | H31: Mercado LLC | I31: =_xlfn.MINIFS(F:F,B:B,B31) -> 44849 | J31: =IF(F31=I31,"Yes","No") -> No | P31: Jul-2021 | Q31: 177849
A32: 30 | B32: 277 | D32: Equipment | E32: Low level | F32: 44200 | G32: 44389 | H32: Smith-Guerrero | I32: =_xlfn.MINIFS(F:F,B:B,B32) -> 44200 | J32: =IF(F32=I32,"Yes","No") -> Yes | P32: Jul-2022 | Q32: 145055
A33: 31 | B33: 2000 | D33: Equipment | E33: Low level | F33: 44085 | G33: 44304 | H33: Moore-Carlson | I33: =_xlfn.MINIFS(F:F,B:B,B33) -> 44085 | J33: =IF(F33=I33,"Yes","No") -> Yes | P33: Jul-2023 | Q33: 152853
A34: 32 | B34: 1228 | D34: Personal Budget | E34: Long Term | F34: 45445 | G34: 45513 | H34: Navarro Group | I34: =_xlfn.MINIFS(F:F,B:B,B34) -> 45445 | J34: =IF(F34=I34,"True","False") -> True | K34: =TEXT(F32,"mmm-yyyy") -> Jan-2021 | P34: Jul-2024 | Q34: 184439
A35: 33 | B35: 3753 | D35: Personal Budget | E35: Long Term | F35: 44365 | G35: 44992 | H35: Williams Group | I35: =_xlfn.MINIFS(F:F,B:B,B35) -> 44365 | J35: =IF(F35=I35,"True","False") -> True | K35: =TEXT(F33,"mmm-yyyy") -> Sep-2020 | P35: Jun-2020 | Q35: 163370
A36: 34 | B36: 3736 | D36: Nursing Home | E36: Long Term | F36: 44755 | G36: 44997 | H36: Wright-Tucker | I36: =_xlfn.MINIFS(F:F,B:B,B36) -> 43980 | J36: =IF(F36=I36,"True","False") -> False | K36: =TEXT(F34,"mmm-yyyy") -> Jun-2024 | P36: Jun-2021 | Q36: 166129
A37: 35 | B37: 696 | D37: Direct Payment | E37: Long Term | F37: 44177 | H37: Bautista Ltd | I37: =_xlfn.MINIFS(F:F,B:B,B37) -> 44177 | J37: =IF(F37=I37,"True","False") -> True | K37: =TEXT(F35,"mmm-yyyy") -> Jun-2021 | P37: Jun-2022 | Q37: 188501
A38: 36 | B38: 1310 | D38: Equipment | E38: Low level | F38: 45112 | G38: 45214 | H38: Harper Group | I38: =_xlfn.MINIFS(F:F,B:B,B38) -> 45112 | J38: =IF(F38=I38,"Yes","No") -> Yes | P38: Jun-2023 | Q38: 160176
A39: 37 | B39: 4153 | D39: Equipment | E39: Low level | F39: 44344 | G39: 44625 | H39: Bennett, Campos and Sanchez | I39: =_xlfn.MINIFS(F:F,B:B,B39) -> 44344 | J39: =IF(F39=I39,"Yes","No") -> Yes | P39: Jun-2024 | Q39: 166040
A40: 38 | B40: 3235 | D40: Equipment | E40: Low level | F40: 45290 | G40: 45445 | H40: Perez-Cervantes | I40: =_xlfn.MINIFS(F:F,B:B,B40) -> 44575 | J40: =IF(F40=I40,"Yes","No") -> No | P40: Mar-2020 | Q40: 161757
A41: 39 | B41: 4115 | D41: Equipment | E41: Low level | F41: 44939 | H41: Griffith PLC | I41: =_xlfn.MINIFS(F:F,B:B,B41) -> 44116 | J41: =IF(F41=I41,"Yes","No") -> No | P41: Mar-2021 | Q41: 166571
A42: 40 | B42: 2312 | D42: Residential Home | E42: Short Term | F42: 44419 | G42: 44453 | H42: Kaufman LLC | I42: =_xlfn.MINIFS(F:F,B:B,B42) -> 44141 | J42: =IF(F42=I42,"Yes","No") -> No | P42: Mar-2022 | Q42: 183461
A43: 41 | B43: 2842 | C43: =_xlfn.XLOOKUP(A41,'New People Info'!A:A,'New People Info'!C:C) -> 0 | D43: Direct Payment | E43: Long Term | F43: 45074 | G43: 45469 | H43: Murray LLC | I43: =_xlfn.MINIFS(F:F,B:B,B43) -> 44121 | J43: =IF(F43=I43,"True","False") -> False | K43: =TEXT(F41,"mmm-yyyy") -> Jan-2023 | P43: Mar-2023 | Q43: 174875
A44: 42 | B44: 4209 | C44: =_xlfn.XLOOKUP(A42,'New People Info'!A:A,'New People Info'!C:C) -> 0 | D44: Homecare | E44: Long Term | F44: 45032 | H44: Daniels, Rodriguez and Oliver | I44: =_xlfn.MINIFS(F:F,B:B,B44) -> 45032 | J44: =IF(F44=I44,"True","False") -> True | K44: =TEXT(F42,"mmm-yyyy") -> Aug-2021 | P44: Mar-2024 | Q44: 124915
A45: 43 | B45: 3560 | D45: Homecare | E45: Long Term | F45: 44372 | G45: 45216 | H45: Brown-Smith | I45: =_xlfn.MINIFS(F:F,B:B,B45) -> 44372 | J45: =IF(F45=I45,"True","False") -> True | K45: =TEXT(F43,"mmm-yyyy") -> May-2023 | P45: May-2020 | Q45: 145339
A46: 44 | B46: 3399 | D46: Nursing Home | E46: Long Term | F46: 44141 | G46: 45150 | H46: Boyer, Barrera and Williams | I46: =_xlfn.MINIFS(F:F,B:B,B46) -> 43820 | J46: =IF(F46=I46,"True","False") -> False | K46: =TEXT(F44,"mmm-yyyy") -> Apr-2023 | P46: May-2021 | Q46: 186775
A47: 45 | B47: 542 | D47: Residential Home | E47: Long Term | F47: 44999 | G47: 45525 | H47: Romero, Duncan and Williams | I47: =_xlfn.MINIFS(F:F,B:B,B47) -> 44999 | J47: =IF(F47=I47,"True","False") -> True | K47: =TEXT(F45,"mmm-yyyy") -> Jun-2021 | P47: May-2022 | Q47: 178892
A48: 46 | B48: 2695 | D48: Equipment | E48: Low level | F48: 45502 | H48: Moran-Davis | I48: =_xlfn.MINIFS(F:F,B:B,B48) -> 43903 | J48: =IF(F48=I48,"Yes","No") -> No | P48: May-2023 | Q48: 122183
A49: 47 | B49: 4675 | D49: Equipment | E49: Low level | F49: 45490 | G49: 45508 | H49: Carter-Dominguez | I49: =_xlfn.MINIFS(F:F,B:B,B49) -> 44448 | J49: =IF(F49=I49,"Yes","No") -> No | P49: May-2024 | Q49: 185072
A50: 48 | B50: 1089 | D50: Personal Budget | E50: Long Term | F50: 44222 | G50: 44849 | H50: Fuller LLC | I50: =_xlfn.MINIFS(F:F,B:B,B50) -> 44222 | J50: =IF(F50=I50,"True","False") -> True | K50: =TEXT(F48,"mmm-yyyy") -> Jul-2024 | P50: Nov-2019 | Q50: 137417
A51: 49 | B51: 3364 | D51: Personal Budget | E51: Long Term | F51: 44651 | G51: 45255 | H51: Suarez, Miller and Wright | I51: =_xlfn.MINIFS(F:F,B:B,B51) -> 44651 | J51: =IF(F51=I51,"True","False") -> True | K51: =TEXT(F49,"mmm-yyyy") -> Jul-2024 | P51: Nov-2020 | Q51: 179278
A52: 50 | B52: 25 | D52: Nursing Home | E52: Long Term | F52: 45433 | H52: Morgan-Mckay | I52: =_xlfn.MINIFS(F:F,B:B,B52) -> 44264 | J52: =IF(F52=I52,"True","False") -> False | K52: =TEXT(F50,"mmm-yyyy") -> Jan-2021 | P52: Nov-2021 | Q52: 161782
A53: 51 | B53: 1573 | D53: Equipment | E53: Low level | F53: 44147 | H53: Pham, Owens and Ferguson | I53: =_xlfn.MINIFS(F:F,B:B,B53) -> 44147 | J53: =IF(F53=I53,"Yes","No") -> Yes | P53: Nov-2022 | Q53: 206283
A54: 52 | B54: 2959 | C54: =_xlfn.XLOOKUP(A52,'New People Info'!A:A,'New People Info'!C:C) -> 0 | D54: Nursing Home | E54: Long Term | F54: 45249 | G54: 45410 | H54: Booker-Mckinney | I54: =_xlfn.MINIFS(F:F,B:B,B54) -> 45249 | J54: =IF(F54=I54,"True","False") -> True | K54: =TEXT(F52,"mmm-yyyy") -> May-2024 | P54: Nov-2023 | Q54: 149512
A55: 53 | B55: 4237 | C55: =_xlfn.XLOOKUP(A53,'New People Info'!A:A,'New People Info'!C:C) -> 0 | D55: Residential Home | E55: Long Term | F55: 45102 | H55: Crane-King | I55: =_xlfn.MINIFS(F:F,B:B,B55) -> 44961 | J55: =IF(F55=I55,"True","False") -> False | K55: =TEXT(F53,"mmm-yyyy") -> Nov-2020 | P55: Oct-2019 | Q55: 177068
A56: 54 | B56: 1768 | D56: Homecare | E56: Long Term | F56: 44978 | G56: 45253 | H56: Phillips Group | I56: =_xlfn.MINIFS(F:F,B:B,B56) -> 44570 | J56: =IF(F56=I56,"True","False") -> False | K56: =TEXT(F54,"mmm-yyyy") -> Nov-2023 | P56: Oct-2020 | Q56: 174239
A57: 55 | B57: 4744 | D57: Equipment | E57: Low level | F57: 45088 | G57: 45287 | H57: Baker-Cowan | I57: =_xlfn.MINIFS(F:F,B:B,B57) -> 45088 | J57: =IF(F57=I57,"Yes","No") -> Yes | P57: Oct-2021 | Q57: 148688
A58: 56 | B58: 2236 | D58: Direct Payment | E58: Long Term | F58: 45387 | G58: 45465 | H58: Lucas and Sons | I58: =_xlfn.MINIFS(F:F,B:B,B58) -> 45161 | J58: =IF(F58=I58,"True","False") -> False | K58: =TEXT(F56,"mmm-yyyy") -> Feb-2023 | P58: Oct-2022 | Q58: 174830
A59: 57 | B59: 201 | D59: Residential Home | E59: Long Term | F59: 44576 | G59: 45511 | H59: Brennan, Grant and Williams | I59: =_xlfn.MINIFS(F:F,B:B,B59) -> 44576 | J59: =IF(F59=I59,"True","False") -> True | K59: =TEXT(F57,"mmm-yyyy") -> Jun-2023 | P59: Oct-2023 | Q59: 144542
A60: 58 | B60: 3199 | D60: Equipment | E60: Low level | F60: 45450 | H60: Branch PLC | I60: =_xlfn.MINIFS(F:F,B:B,B60) -> 45450 | J60: =IF(F60=I60,"Yes","No") -> Yes | P60: Sep-2019 | Q60: 153800
A61: 59 | B61: 257 | D61: Direct Payment | E61: Long Term | F61: 44528 | H61: Williams Ltd | I61: =_xlfn.MINIFS(F:F,B:B,B61) -> 43971 | J61: =IF(F61=I61,"True","False") -> False | K61: =TEXT(F59,"mmm-yyyy") -> Jan-2022 | P61: Sep-2020 | Q61: 142648
A62: 60 | B62: 3748 | D62: Personal Budget | E62: Long Term | F62: 43822 | H62: Kennedy, Reynolds and Sanchez | I62: =_xlfn.MINIFS(F:F,B:B,B62) -> 43822 | J62: =IF(F62=I62,"True","False") -> True | K62: =TEXT(F60,"mmm-yyyy") -> Jun-2024 | P62: Sep-2021 | Q62: 153661
A63: 61 | B63: 4643 | D63: Nursing Home | E63: Long Term | F63: 44048 | G63: 45347 | H63: Carpenter, Hicks and Estrada | I63: =_xlfn.MINIFS(F:F,B:B,B63) -> 44048 | J63: =IF(F63=I63,"True","False") -> True | K63: =TEXT(F61,"mmm-yyyy") -> Nov-2021 | P63: Sep-2022 | Q63: 175614
A64: 62 | B64: 2242 | D64: Personal Budget | E64: Long Term | F64: 43753 | G64: 45106 | H64: Carey, Anderson and Fisher | I64: =_xlfn.MINIFS(F:F,B:B,B64) -> 43753 | J64: =IF(F64=I64,"True","False") -> True | K64: =TEXT(F62,"mmm-yyyy") -> Dec-2019 | P64: Sep-2023 | Q64: 160472
A65: 63 | B65: 3176 | D65: Homecare | E65: Long Term | F65: 43707 | H65: Mccann Inc | I65: =_xlfn.MINIFS(F:F,B:B,B65) -> 43707 | J65: =IF(F65=I65,"True","False") -> True | K65: =TEXT(F63,"mmm-yyyy") -> Aug-2020 | P65: Start Date | Q65: 3823
A66: 64 | B66: 3607 | D66: Personal Budget | E66: Long Term | F66: 44895 | G66: 45280 | H66: Miller, Page and Lynn | I66: =_xlfn.MINIFS(F:F,B:B,B66) -> 43756 | J66: =IF(F66=I66,"True","False") -> False | K66: =TEXT(F64,"mmm-yyyy") -> Oct-2019 | P66: Grand Total | Q66: 9867164
A67: 65 | B67: 3337 | D67: Equipment | E67: Low level | F67: 43827 | G67: 45039 | H67: Clark-Weber | I67: =_xlfn.MINIFS(F:F,B:B,B67) -> 43827 | J67: =IF(F67=I67,"Yes","No") -> Yes
A68: 66 | B68: 4898 | C68: =_xlfn.XLOOKUP(A66,'New People Info'!A:A,'New People Info'!C:C) -> 0 | D68: Direct Payment | E68: Long Term | F68: 45197 | G68: 45254 | H68: Oconnor Group | I68: =_xlfn.MINIFS(F:F,B:B,B68) -> 44493 | J68: =IF(F68=I68,"True","False") -> False | K68: =TEXT(F66,"mmm-yyyy") -> Nov-2022
A69: 67 | B69: 414 | D69: Personal Budget | E69: Long Term | F69: 44599 | H69: Acosta, Roberts and Rivera | I69: =_xlfn.MINIFS(F:F,B:B,B69) -> 44537 | J69: =IF(F69=I69,"True","False") -> False | K69: =TEXT(F67,"mmm-yyyy") -> Dec-2019
A70: 68 | B70: 2015 | D70: Equipment | E70: Low level | F70: 44241 | G70: 44273 | H70: Perez, Thomas and Moore | I70: =_xlfn.MINIFS(F:F,B:B,B70) -> 44241 | J70: =IF(F70=I70,"Yes","No") -> Yes
A71: 69 | B71: 1382 | C71: =_xlfn.XLOOKUP(A69,'New People Info'!A:A,'New People Info'!C:C) -> 0 | D71: Homecare | E71: Long Term | F71: 45237 | H71: Weaver, Whitehead and Carter | I71: =_xlfn.MINIFS(F:F,B:B,B71) -> 45167 | J71: =IF(F71=I71,"True","False") -> False | K71: =TEXT(F69,"mmm-yyyy") -> Feb-2022
A72: 70 | B72: 1099 | D72: Direct Payment | E72: Long Term | F72: 45464 | G72: 45475 | H72: Floyd, Love and Weber | I72: =_xlfn.MINIFS(F:F,B:B,B72) -> 43741 | J72: =IF(F72=I72,"True","False") -> False | K72: =TEXT(F70,"mmm-yyyy") -> Feb-2021
A73: 71 | B73: 3427 | D73: Personal Budget | E73: Long Term | F73: 44973 | G73: 45149 | H73: Smith LLC | I73: =_xlfn.MINIFS(F:F,B:B,B73) -> 43792 | J73: =IF(F73=I73,"True","False") -> False | K73: =TEXT(F71,"mmm-yyyy") -> Nov-2023
A74: 72 | B74: 3656 | D74: Nursing Home | E74: Long Term | F74: 44206 | G74: 44265 | H74: Kennedy and Sons | I74: =_xlfn.MINIFS(F:F,B:B,B74) -> 44206 | J74: =IF(F74=I74,"True","False") -> True | K74: =TEXT(F72,"mmm-yyyy") -> Jun-2024
A75: 73 | B75: 910 | C75: =_xlfn.XLOOKUP(A73,'New People Info'!A:A,'New People Info'!C:C) -> 0 | D75: Nursing Home | E75: Long Term | F75: 45158 | G75: 45354 | H75: Williams-Cooper | I75: =_xlfn.MINIFS(F:F,B:B,B75) -> 45158 | J75: =IF(F75=I75,"True","False") -> True | K75: =TEXT(F73,"mmm-yyyy") -> Feb-2023
A76: 74 | B76: 188 | C76: =_xlfn.XLOOKUP(A74,'New People Info'!A:A,'New People Info'!C:C) -> 0 | D76: Direct Payment | E76: Long Term | F76: 45105 | G76: 45280 | H76: Woodward-Huber | I76: =_xlfn.MINIFS(F:F,B:B,B76) -> 45105 | J76: =IF(F76=I76,"True","False") -> True | K76: =TEXT(F74,"mmm-yyyy") -> Jan-2021
A77: 75 | B77: 4045 | D77: Nursing Home | E77: Long Term | F77: 45417 | G77: 45526 | H77: Herrera, Martin and Gibson | I77: =_xlfn.MINIFS(F:F,B:B,B77) -> 43725 | J77: =IF(F77=I77,"True","False") -> False | K77: =TEXT(F75,"mmm-yyyy") -> Aug-2023
A78: 76 | B78: 3757 | D78: Personal Budget | E78: Long Term | F78: 44312 | H78: Nunez Inc | I78: =_xlfn.MINIFS(F:F,B:B,B78) -> 44312 | J78: =IF(F78=I78,"True","False") -> True | K78: =TEXT(F76,"mmm-yyyy") -> Jun-2023
A79: 77 | B79: 2016 | D79: Personal Budget | E79: Long Term | F79: 44694 | G79: 44886 | H79: Marshall Group | I79: =_xlfn.MINIFS(F:F,B:B,B79) -> 44694 | J79: =IF(F79=I79,"True","False") -> True | K79: =TEXT(F77,"mmm-yyyy") -> May-2024
A80: 78 | B80: 2093 | D80: Direct Payment | E80: Long Term | F80: 43751 | G80: 45089 | H80: Bryant, Lopez and Thompson | I80: =_xlfn.MINIFS(F:F,B:B,B80) -> 43751 | J80: =IF(F80=I80,"True","False") -> True | K80: =TEXT(F78,"mmm-yyyy") -> Apr-2021
A81: 79 | B81: 3645 | D81: Personal Budget | E81: Long Term | F81: 44067 | G81: 45331 | H81: Martin LLC | I81: =_xlfn.MINIFS(F:F,B:B,B81) -> 44067 | J81: =IF(F81=I81,"True","False") -> True | K81: =TEXT(F79,"mmm-yyyy") -> May-2022
A82: 80 | B82: 2131 | D82: Equipment | E82: Low level | F82: 44546 | G82: 45415 | H82: Carlson-Little | I82: =_xlfn.MINIFS(F:F,B:B,B82) -> 44546 | J82: =IF(F82=I82,"Yes","No") -> Yes
A83: 81 | B83: 358 | C83: =_xlfn.XLOOKUP(A81,'New People Info'!A:A,'New People Info'!C:C) -> 0 | D83: Homecare | E83: Long Term | F83: 45093 | G83: 45489 | H83: Glass Ltd | I83: =_xlfn.MINIFS(F:F,B:B,B83) -> 45093 | J83: =IF(F83=I83,"True","False") -> True | K83: =TEXT(F81,"mmm-yyyy") -> Aug-2020
A84: 82 | B84: 2423 | D84: Nursing Home | E84: Long Term | F84: 44894 | H84: Compton Ltd | I84: =_xlfn.MINIFS(F:F,B:B,B84) -> 44894 | J84: =IF(F84=I84,"True","False") -> True | K84: =TEXT(F82,"mmm-yyyy") -> Dec-2021
A85: 83 | B85: 4258 | D85: Equipment | E85: Low level | F85: 44672 | G85: 45213 | H85: Smith-Perry | I85: =_xlfn.MINIFS(F:F,B:B,B85) -> 44672 | J85: =IF(F85=I85,"Yes","No") -> Yes
A86: 84 | B86: 4546 | C86: =_xlfn.XLOOKUP(A84,'New People Info'!A:A,'New People Info'!C:C) -> 0 | D86: Direct Payment | E86: Long Term | F86: 45120 | H86: Adams, Smith and Coleman | I86: =_xlfn.MINIFS(F:F,B:B,B86) -> 44152 | J86: =IF(F86=I86,"True","False") -> False | K86: =TEXT(F84,"mmm-yyyy") -> Nov-2022
A87: 85 | B87: 1498 | D87: Nursing Home | E87: Long Term | F87: 44470 | G87: 45328 | H87: Jones-Cantu | I87: =_xlfn.MINIFS(F:F,B:B,B87) -> 44241 | J87: =IF(F87=I87,"True","False") -> False | K87: =TEXT(F85,"mmm-yyyy") -> Apr-2022
A88: 86 | B88: 2159 | D88: Equipment | E88: Low level | F88: 45305 | H88: West-Stevens | I88: =_xlfn.MINIFS(F:F,B:B,B88) -> 44246 | J88: =IF(F88=I88,"Yes","No") -> No
A89: 87 | B89: 2556 | D89: Personal Budget | E89: Long Term | F89: 43834 | G89: 44248 | H89: Stewart, Johnson and Johnson | I89: =_xlfn.MINIFS(F:F,B:B,B89) -> 43834 | J89: =IF(F89=I89,"True","False") -> True | K89: =TEXT(F87,"mmm-yyyy") -> Oct-2021
A90: 88 | B90: 2343 | D90: Direct Payment | E90: Long Term | F90: 44684 | G90: 44722 | H90: Ross Ltd | I90: =_xlfn.MINIFS(F:F,B:B,B90) -> 44684 | J90: =IF(F90=I90,"True","False") -> True | K90: =TEXT(F88,"mmm-yyyy") -> Jan-2024
A91: 89 | B91: 2952 | D91: Direct Payment | E91: Long Term | F91: 44529 | G91: 44543 | H91: Walker LLC | I91: =_xlfn.MINIFS(F:F,B:B,B91) -> 44529 | J91: =IF(F91=I91,"True","False") -> True | K91: =TEXT(F89,"mmm-yyyy") -> Jan-2020
A92: 90 | B92: 1239 | D92: Nursing Home | E92: Long Term | F92: 44339 | G92: 44631 | H92: Petersen, Moore and Spencer | I92: =_xlfn.MINIFS(F:F,B:B,B92) -> 44339 | J92: =IF(F92=I92,"True","False") -> True | K92: =TEXT(F90,"mmm-yyyy") -> May-2022
A93: 91 | B93: 974 | D93: Personal Budget | E93: Short Term | F93: 45113 | G93: 45119 | H93: Williams LLC | I93: =_xlfn.MINIFS(F:F,B:B,B93) -> 45113 | J93: =IF(F93=I93,"Yes","No") -> Yes
A94: 92 | B94: 4728 | D94: Nursing Home | E94: Long Term | F94: 44622 | H94: Smith and Sons | I94: =_xlfn.MINIFS(F:F,B:B,B94) -> 44312 | J94: =IF(F94=I94,"True","False") -> False | K94: =TEXT(F92,"mmm-yyyy") -> May-2021
A95: 93 | B95: 3966 | D95: Residential Home | E95: Long Term | F95: 44119 | H95: Miller-Garcia | I95: =_xlfn.MINIFS(F:F,B:B,B95) -> 44119 | J95: =IF(F95=I95,"True","False") -> True | K95: =TEXT(F93,"mmm-yyyy") -> Jul-2023
A96: 94 | B96: 1051 | D96: Equipment | E96: Low level | F96: 43990 | G96: 44589 | H96: Nguyen, Johnson and Ramos | I96: =_xlfn.MINIFS(F:F,B:B,B96) -> 43990 | J96: =IF(F96=I96,"Yes","No") -> Yes
A97: 95 | B97: 3702 | D97: Residential Home | E97: Long Term | F97: 44175 | G97: 44569 | H97: Ferguson Inc | I97: =_xlfn.MINIFS(F:F,B:B,B97) -> 44175 | J97: =IF(F97=I97,"True","False") -> True | K97: =TEXT(F95,"mmm-yyyy") -> Oct-2020
A98: 96 | B98: 2781 | D98: Equipment | E98: Low level | F98: 44865 | G98: 45531 | H98: Blankenship LLC | I98: =_xlfn.MINIFS(F:F,B:B,B98) -> 43748 | J98: =IF(F98=I98,"Yes","No") -> No
A99: 97 | B99: 1589 | C99: =_xlfn.XLOOKUP(A97,'New People Info'!A:A,'New People Info'!C:C) -> 0 | D99: Homecare | E99: Long Term | F99: 45120 | G99: 45191 | H99: Smith, Perez and Miller | I99: =_xlfn.MINIFS(F:F,B:B,B99) -> 45120 | J99: =IF(F99=I99,"True","False") -> True | K99: =TEXT(F97,"mmm-yyyy") -> Dec-2020
A100: 98 | B100: 3879 | C100: =_xlfn.XLOOKUP(A98,'New People Info'!A:A,'New People Info'!C:C) -> 0 | D100: Direct Payment | E100: Long Term | F100: 45367 | G100: 45524 | H100: Hernandez, Perez and Harmon | I100: =_xlfn.MINIFS(F:F,B:B,B100) -> 44198 | J100: =IF(F100=I100,"True","False") -> False | K100: =TEXT(F98,"mmm-yyyy") -> Oct-2022
...

Sheet Dashboard 2
A1: Number of People with Autism and the Median Calendar Days from Assessment to Long Term Calendar Days for New People
I4: Question 3
A25: Q4: Median Number of Calendar Days for New People:
A26: {=_xlfn.LET( _xlpm.svc_class, 'New services table '!$D$2:$D$5001, _xlpm.svc_first, 'New services table '!$I$2:$I$5001, _xlpm.svc_start, 'New services table '!$E$2:$E$5001, _xlpm.svc_person, 'New services table '!$B$2:$B$5001, _xlpm.assess_person, 'New assessments completed'!$A$2:$A$1089, _xlpm.assess_end, 'New assessments completed'!$D$2:$D$1089, _xlpm.year_start, DATE(2023,4,1), _xlpm.year_end, DATE(2024,3,31), _xlpm.is_new, (_xlpm.svc_class="Long Term") * ((_xlpm.svc_first="Yes") + (_xlpm.svc_first=TRUE)) * (_xlpm.svc_start>=_xlpm.year_start) * (_xlpm.svc_start<=_xlpm.year_end), _xlpm.days_diff, IF(_xlpm.is_new, _xlpm.svc_start - _xlfn.XLOOKUP(_xlpm.svc_person, _xlpm.assess_person, _xlpm.assess_end, NA()), NA()), MEDIAN(IF(ISNUMBER(_xlpm.days_diff), _xlpm.days_diff)) )} -> 28

Sheet Dashboard 3
A25: New People: | C25: 3937 | J25: Median Number of Calendar Days: | R25: {=_xlfn.LET( _xlpm.svc_class, 'New services table '!$D$2:$D$5001, _xlpm.svc_first, 'New services table '!$I$2:$I$5001, _xlpm.svc_start, 'New services table '!$E$2:$E$5001, _xlpm.svc_person, 'New services table '!$B$2:$B$5001, _xlpm.assess_person, 'New assessments completed'!$A$2:$A$1089, _xlpm.assess_end, 'New assessments completed'!$D$2:$D$1089, _xlpm.year_start, DATE(2023,4,1), _xlpm.year_end, DATE(2024,3,31), _xlpm.is_new, (_xlpm.svc_class="Long Term") * ((_xlpm.svc_first="Yes") + (_xlpm.svc_first=TRUE)) * (_xlpm.svc_start>=_xlpm.year_start) * (_xlpm.svc_start<=_xlpm.year_end), _xlpm.days_diff, IF(_xlpm.is_new, _xlpm.svc_start - _xlfn.XLOOKUP(_xlpm.svc_person, _xlpm.assess_person, _xlpm.assess_end, NA()), NA()), MEDIAN(IF(ISNUMBER(_xlpm.days_diff), _xlpm.days_diff)) )} -> 28
A28: Number of People Who Have Autism: | F28: 3

Sheet Insights
